{
  "sport": "SOCCER",
  "date": "2026-06-23",
  "last_updated": "2:50 PM ET",
  "pinned_board": {
    "title": "Anytime Goalscorer Top 10",
    "market": "GS",
    "players": [
      {
        "player_id": "142200",
        "player_name": "Harry Kane",
        "team": "ENG",
        "opponent": "GHA",
        "line": "Anytime Goal",
        "score": 84.45,
        "confidence": 84,
        "tier": "A",
        "reason": "Goal \u03bb 1.86 | Raw G/m 1.36 | Team xG 2.51 | Sample 47 | FIFA World Cup | Shrunk to F prior",
        "sim_prob_pct": 84.45,
        "model_hit_rate": 0.8445
      },
      {
        "player_id": "268782",
        "player_name": "Anthony Gordon",
        "team": "ENG",
        "opponent": "GHA",
        "line": "Anytime Goal",
        "score": 70.73,
        "confidence": 71,
        "tier": "B",
        "reason": "Goal \u03bb 1.23 | Raw G/m 1.00 | Team xG 2.51 | Sample 12 | FIFA World Cup | Shrunk to F prior",
        "sim_prob_pct": 70.73,
        "model_hit_rate": 0.7073
      },
      {
        "player_id": "288896",
        "player_name": "Gon\u00e7alo Ramos",
        "team": "POR",
        "opponent": "UZB",
        "line": "Anytime Goal",
        "score": 69.8,
        "confidence": 70,
        "tier": "B",
        "reason": "Goal \u03bb 1.20 | Raw G/m 1.25 | Team xG 2.67 | Sample 4 | FIFA World Cup | Shrunk to F prior",
        "sim_prob_pct": 69.8,
        "model_hit_rate": 0.698
      },
      {
        "player_id": "180639",
        "player_name": "Ivan Toney",
        "team": "ENG",
        "opponent": "GHA",
        "line": "Anytime Goal",
        "score": 69.59,
        "confidence": 70,
        "tier": "B",
        "reason": "Goal \u03bb 1.19 | Raw G/m 0.87 | Team xG 2.51 | Sample 39 | FIFA World Cup | Shrunk to F prior",
        "sim_prob_pct": 69.59,
        "model_hit_rate": 0.6959
      },
      {
        "player_id": "22774",
        "player_name": "Cristiano Ronaldo",
        "team": "POR",
        "opponent": "UZB",
        "line": "Anytime Goal",
        "score": 65.72,
        "confidence": 66,
        "tier": "B",
        "reason": "Goal \u03bb 1.07 | Raw G/m 0.78 | Team xG 2.67 | Sample 37 | FIFA World Cup | Shrunk to F prior",
        "sim_prob_pct": 65.72,
        "model_hit_rate": 0.6572
      },
      {
        "player_id": "277128",
        "player_name": "Petar Musa",
        "team": "CRO",
        "opponent": "PAN",
        "line": "Anytime Goal",
        "score": 63.45,
        "confidence": 63,
        "tier": "B",
        "reason": "Goal \u03bb 1.01 | Raw G/m 0.93 | Team xG 2.05 | Sample 14 | FIFA World Cup | Shrunk to F prior",
        "sim_prob_pct": 63.45,
        "model_hit_rate": 0.6345
      },
      {
        "player_id": "230945",
        "player_name": "Marcus Rashford",
        "team": "ENG",
        "opponent": "GHA",
        "line": "Anytime Goal",
        "score": 57.92,
        "confidence": 58,
        "tier": "B",
        "reason": "Goal \u03bb 0.87 | Raw G/m 0.70 | Team xG 2.51 | Sample 10 | FIFA World Cup | Shrunk to F prior",
        "sim_prob_pct": 57.92,
        "model_hit_rate": 0.5792
      },
      {
        "player_id": "272722",
        "player_name": "Luis Su\u00e1rez",
        "team": "COL",
        "opponent": "COD",
        "line": "Anytime Goal",
        "score": 57.65,
        "confidence": 58,
        "tier": "B",
        "reason": "Goal \u03bb 0.86 | Raw G/m 0.76 | Team xG 1.85 | Sample 49 | FIFA World Cup | Shrunk to F prior",
        "sim_prob_pct": 57.65,
        "model_hit_rate": 0.5765
      },
      {
        "player_id": "276350",
        "player_name": "Jo\u00e3o F\u00e9lix",
        "team": "POR",
        "opponent": "UZB",
        "line": "Anytime Goal",
        "score": 56.95,
        "confidence": 57,
        "tier": "B",
        "reason": "Goal \u03bb 0.84 | Raw G/m 0.61 | Team xG 2.67 | Sample 41 | FIFA World Cup | Shrunk to F prior",
        "sim_prob_pct": 56.95,
        "model_hit_rate": 0.5695
      },
      {
        "player_id": "189668",
        "player_name": "Mario Pasalic",
        "team": "CRO",
        "opponent": "PAN",
        "line": "Anytime Goal",
        "score": 54.58,
        "confidence": 55,
        "tier": "C",
        "reason": "Goal \u03bb 0.79 | Raw G/m 0.80 | Team xG 2.05 | Sample 10 | FIFA World Cup | Shrunk to M prior",
        "sim_prob_pct": 54.58,
        "model_hit_rate": 0.5458
      }
    ]
  },
  "games": [
    {
      "game_id": "760461",
      "matchup": "UZB @ POR",
      "time": "FIFA World Cup | 86'",
      "top_signals": [
        {
          "market": "SOT",
          "player_name": "Gon\u00e7alo Ramos",
          "line": "2+ Shots on Goal",
          "score": 83.68,
          "confidence": 84,
          "tier": "A",
          "player_id": "288896"
        },
        {
          "market": "SHOTS",
          "player_name": "Cristiano Ronaldo",
          "line": "2+ Shots",
          "score": 99.0,
          "confidence": 99,
          "tier": "A",
          "player_id": "22774"
        },
        {
          "market": "BTTS",
          "player_name": "Both Teams to Score",
          "line": "BTTS No",
          "score": 51.93,
          "confidence": 52,
          "tier": "C",
          "player_id": "760461-btts"
        }
      ],
      "markets": {
        "GS": [
          {
            "player_id": "288896",
            "player_name": "Gon\u00e7alo Ramos",
            "team": "POR",
            "opponent": "UZB",
            "line": "Anytime Goal",
            "score": 69.8,
            "confidence": 70,
            "tier": "B",
            "reason": "Goal \u03bb 1.20 | Raw G/m 1.25 | Team xG 2.67 | Sample 4 | FIFA World Cup | Shrunk to F prior",
            "sim_prob_pct": 69.8,
            "model_hit_rate": 0.698
          },
          {
            "player_id": "22774",
            "player_name": "Cristiano Ronaldo",
            "team": "POR",
            "opponent": "UZB",
            "line": "Anytime Goal",
            "score": 65.72,
            "confidence": 66,
            "tier": "B",
            "reason": "Goal \u03bb 1.07 | Raw G/m 0.78 | Team xG 2.67 | Sample 37 | FIFA World Cup | Shrunk to F prior",
            "sim_prob_pct": 65.72,
            "model_hit_rate": 0.6572
          },
          {
            "player_id": "276350",
            "player_name": "Jo\u00e3o F\u00e9lix",
            "team": "POR",
            "opponent": "UZB",
            "line": "Anytime Goal",
            "score": 56.95,
            "confidence": 57,
            "tier": "B",
            "reason": "Goal \u03bb 0.84 | Raw G/m 0.61 | Team xG 2.67 | Sample 41 | FIFA World Cup | Shrunk to F prior",
            "sim_prob_pct": 56.95,
            "model_hit_rate": 0.5695
          },
          {
            "player_id": "213141",
            "player_name": "Gon\u00e7alo Guedes",
            "team": "POR",
            "opponent": "UZB",
            "line": "Anytime Goal",
            "score": 39.92,
            "confidence": 40,
            "tier": "C",
            "reason": "Goal \u03bb 0.51 | Raw G/m 0.40 | Team xG 2.67 | Sample 5 | FIFA World Cup | Shrunk to F prior",
            "sim_prob_pct": 39.92,
            "model_hit_rate": 0.3992
          },
          {
            "player_id": "256115",
            "player_name": "Pedro Neto",
            "team": "POR",
            "opponent": "UZB",
            "line": "Anytime Goal",
            "score": 37.23,
            "confidence": 37,
            "tier": "C",
            "reason": "Goal \u03bb 0.47 | Raw G/m 0.33 | Team xG 2.67 | Sample 15 | FIFA World Cup | Shrunk to F prior",
            "sim_prob_pct": 37.23,
            "model_hit_rate": 0.3723
          },
          {
            "player_id": "258917",
            "player_name": "Rafael Le\u00e3o",
            "team": "POR",
            "opponent": "UZB",
            "line": "Anytime Goal",
            "score": 35.6,
            "confidence": 36,
            "tier": "C",
            "reason": "Goal \u03bb 0.44 | Raw G/m 0.33 | Team xG 2.67 | Sample 3 | FIFA World Cup | Shrunk to F prior",
            "sim_prob_pct": 35.6,
            "model_hit_rate": 0.356
          },
          {
            "player_id": "274159",
            "player_name": "Francisco Trinc\u00e3o",
            "team": "POR",
            "opponent": "UZB",
            "line": "Anytime Goal",
            "score": 33.09,
            "confidence": 33,
            "tier": "C",
            "reason": "Goal \u03bb 0.40 | Raw G/m 0.28 | Team xG 2.67 | Sample 50 | FIFA World Cup | Shrunk to F prior",
            "sim_prob_pct": 33.09,
            "model_hit_rate": 0.3309
          },
          {
            "player_id": "208128",
            "player_name": "R\u00faben Neves",
            "team": "POR",
            "opponent": "UZB",
            "line": "Anytime Goal",
            "score": 32.03,
            "confidence": 32,
            "tier": "C",
            "reason": "Goal \u03bb 0.39 | Raw G/m 0.28 | Team xG 2.67 | Sample 39 | FIFA World Cup | Shrunk to M prior",
            "sim_prob_pct": 32.03,
            "model_hit_rate": 0.3203
          },
          {
            "player_id": "216937",
            "player_name": "Eldor Shomurodov",
            "team": "UZB",
            "opponent": "POR",
            "line": "Anytime Goal",
            "score": 31.49,
            "confidence": 31,
            "tier": "C",
            "reason": "Goal \u03bb 0.38 | Raw G/m 0.59 | Team xG 0.73 | Sample 39 | FIFA World Cup | Shrunk to F prior",
            "sim_prob_pct": 31.49,
            "model_hit_rate": 0.3149
          },
          {
            "player_id": "312659",
            "player_name": "Francisco Concei\u00e7\u00e3o",
            "team": "POR",
            "opponent": "UZB",
            "line": "Anytime Goal",
            "score": 30.96,
            "confidence": 31,
            "tier": "C",
            "reason": "Goal \u03bb 0.37 | Raw G/m 0.25 | Team xG 2.67 | Sample 8 | FIFA World Cup | Shrunk to F prior",
            "sim_prob_pct": 30.96,
            "model_hit_rate": 0.3096
          }
        ],
        "AST": [
          {
            "player_id": "213141",
            "player_name": "Gon\u00e7alo Guedes",
            "team": "POR",
            "opponent": "UZB",
            "line": "Assist",
            "score": 54.75,
            "confidence": 55,
            "tier": "C",
            "reason": "Assist \u03bb 0.79 | Raw A/m 0.80 | Team xG 2.67 | Sample 5 | FIFA World Cup | Shrunk to F prior",
            "sim_prob_pct": 54.75,
            "model_hit_rate": 0.5475
          },
          {
            "player_id": "276350",
            "player_name": "Jo\u00e3o F\u00e9lix",
            "team": "POR",
            "opponent": "UZB",
            "line": "Assist",
            "score": 43.35,
            "confidence": 43,
            "tier": "C",
            "reason": "Assist \u03bb 0.57 | Raw A/m 0.41 | Team xG 2.67 | Sample 41 | FIFA World Cup | Shrunk to F prior",
            "sim_prob_pct": 43.35,
            "model_hit_rate": 0.4335
          },
          {
            "player_id": "124091",
            "player_name": "Bruno Fernandes",
            "team": "POR",
            "opponent": "UZB",
            "line": "Assist",
            "score": 42.59,
            "confidence": 43,
            "tier": "C",
            "reason": "Assist \u03bb 0.55 | Raw A/m 0.50 | Team xG 2.67 | Sample 6 | FIFA World Cup | Shrunk to M prior",
            "sim_prob_pct": 42.59,
            "model_hit_rate": 0.4259
          },
          {
            "player_id": "274159",
            "player_name": "Francisco Trinc\u00e3o",
            "team": "POR",
            "opponent": "UZB",
            "line": "Assist",
            "score": 32.33,
            "confidence": 32,
            "tier": "C",
            "reason": "Assist \u03bb 0.39 | Raw A/m 0.28 | Team xG 2.67 | Sample 50 | FIFA World Cup | Shrunk to F prior",
            "sim_prob_pct": 32.33,
            "model_hit_rate": 0.3233
          },
          {
            "player_id": "208128",
            "player_name": "R\u00faben Neves",
            "team": "POR",
            "opponent": "UZB",
            "line": "Assist",
            "score": 30.1,
            "confidence": 30,
            "tier": "C",
            "reason": "Assist \u03bb 0.36 | Raw A/m 0.26 | Team xG 2.67 | Sample 39 | FIFA World Cup | Shrunk to M prior",
            "sim_prob_pct": 30.1,
            "model_hit_rate": 0.301
          },
          {
            "player_id": "256115",
            "player_name": "Pedro Neto",
            "team": "POR",
            "opponent": "UZB",
            "line": "Assist",
            "score": 29.7,
            "confidence": 30,
            "tier": "C",
            "reason": "Assist \u03bb 0.35 | Raw A/m 0.27 | Team xG 2.67 | Sample 15 | FIFA World Cup | Shrunk to F prior",
            "sim_prob_pct": 29.7,
            "model_hit_rate": 0.297
          },
          {
            "player_id": "176399",
            "player_name": "Jo\u00e3o Cancelo",
            "team": "POR",
            "opponent": "UZB",
            "line": "Assist",
            "score": 28.51,
            "confidence": 29,
            "tier": "C",
            "reason": "Assist \u03bb 0.34 | Raw A/m 0.27 | Team xG 2.67 | Sample 15 | FIFA World Cup | Shrunk to D prior",
            "sim_prob_pct": 28.51,
            "model_hit_rate": 0.2851
          },
          {
            "player_id": "238902",
            "player_name": "Diogo Dalot",
            "team": "POR",
            "opponent": "UZB",
            "line": "Assist",
            "score": 25.13,
            "confidence": 25,
            "tier": "C",
            "reason": "Assist \u03bb 0.29 | Raw A/m 0.33 | Team xG 2.67 | Sample 3 | FIFA World Cup | Shrunk to D prior",
            "sim_prob_pct": 25.13,
            "model_hit_rate": 0.2513
          },
          {
            "player_id": "355061",
            "player_name": "Jo\u00e3o Neves",
            "team": "POR",
            "opponent": "UZB",
            "line": "Assist",
            "score": 23.12,
            "confidence": 23,
            "tier": "C",
            "reason": "Assist \u03bb 0.26 | Raw A/m 0.19 | Team xG 2.67 | Sample 16 | FIFA World Cup | Shrunk to M prior",
            "sim_prob_pct": 23.12,
            "model_hit_rate": 0.2312
          },
          {
            "player_id": "312659",
            "player_name": "Francisco Concei\u00e7\u00e3o",
            "team": "POR",
            "opponent": "UZB",
            "line": "Assist",
            "score": 16.91,
            "confidence": 17,
            "tier": "C",
            "reason": "Assist \u03bb 0.19 | Raw A/m 0.12 | Team xG 2.67 | Sample 8 | FIFA World Cup | Shrunk to F prior",
            "sim_prob_pct": 16.91,
            "model_hit_rate": 0.1691
          }
        ],
        "SHOTS": [
          {
            "player_id": "22774",
            "player_name": "Cristiano Ronaldo",
            "team": "POR",
            "opponent": "UZB",
            "line": "2+ Shots",
            "score": 99.0,
            "confidence": 99,
            "tier": "A",
            "reason": "Shots \u03bb 7.03 | Raw shots/m 5.05 | Sample 37 | FIFA World Cup | Shrunk to F prior",
            "sim_prob_pct": 99.0,
            "model_hit_rate": 0.99
          },
          {
            "player_id": "288896",
            "player_name": "Gon\u00e7alo Ramos",
            "team": "POR",
            "opponent": "UZB",
            "line": "2+ Shots",
            "score": 98.56,
            "confidence": 99,
            "tier": "A",
            "reason": "Shots \u03bb 6.22 | Raw shots/m 5.50 | Sample 4 | FIFA World Cup | Shrunk to F prior",
            "sim_prob_pct": 98.56,
            "model_hit_rate": 0.9856
          },
          {
            "player_id": "276350",
            "player_name": "Jo\u00e3o F\u00e9lix",
            "team": "POR",
            "opponent": "UZB",
            "line": "2+ Shots",
            "score": 96.2,
            "confidence": 96,
            "tier": "A",
            "reason": "Shots \u03bb 5.07 | Raw shots/m 3.61 | Sample 41 | FIFA World Cup | Shrunk to F prior",
            "sim_prob_pct": 96.2,
            "model_hit_rate": 0.962
          },
          {
            "player_id": "213141",
            "player_name": "Gon\u00e7alo Guedes",
            "team": "POR",
            "opponent": "UZB",
            "line": "2+ Shots",
            "score": 92.84,
            "confidence": 93,
            "tier": "A",
            "reason": "Shots \u03bb 4.31 | Raw shots/m 3.40 | Sample 5 | FIFA World Cup | Shrunk to F prior",
            "sim_prob_pct": 92.84,
            "model_hit_rate": 0.9284
          },
          {
            "player_id": "312659",
            "player_name": "Francisco Concei\u00e7\u00e3o",
            "team": "POR",
            "opponent": "UZB",
            "line": "2+ Shots",
            "score": 91.96,
            "confidence": 92,
            "tier": "A",
            "reason": "Shots \u03bb 4.16 | Raw shots/m 3.12 | Sample 8 | FIFA World Cup | Shrunk to F prior",
            "sim_prob_pct": 91.96,
            "model_hit_rate": 0.9196
          },
          {
            "player_id": "274159",
            "player_name": "Francisco Trinc\u00e3o",
            "team": "POR",
            "opponent": "UZB",
            "line": "2+ Shots",
            "score": 81.41,
            "confidence": 81,
            "tier": "A",
            "reason": "Shots \u03bb 3.09 | Raw shots/m 2.16 | Sample 50 | FIFA World Cup | Shrunk to F prior",
            "sim_prob_pct": 81.41,
            "model_hit_rate": 0.8141
          },
          {
            "player_id": "288897",
            "player_name": "Vitinha ",
            "team": "POR",
            "opponent": "UZB",
            "line": "2+ Shots",
            "score": 79.48,
            "confidence": 79,
            "tier": "A",
            "reason": "Shots \u03bb 2.96 | Raw shots/m 2.14 | Sample 22 | FIFA World Cup | Shrunk to M prior",
            "sim_prob_pct": 79.48,
            "model_hit_rate": 0.7948
          },
          {
            "player_id": "290591",
            "player_name": "Nuno Mendes",
            "team": "POR",
            "opponent": "UZB",
            "line": "1+ Shots",
            "score": 76.35,
            "confidence": 76,
            "tier": "A",
            "reason": "Shots \u03bb 1.44 | Raw shots/m 1.05 | Sample 20 | FIFA World Cup | Shrunk to D prior",
            "sim_prob_pct": 76.35,
            "model_hit_rate": 0.7635
          },
          {
            "player_id": "256115",
            "player_name": "Pedro Neto",
            "team": "POR",
            "opponent": "UZB",
            "line": "2+ Shots",
            "score": 73.59,
            "confidence": 74,
            "tier": "A",
            "reason": "Shots \u03bb 2.62 | Raw shots/m 1.80 | Sample 15 | FIFA World Cup | Shrunk to F prior",
            "sim_prob_pct": 73.59,
            "model_hit_rate": 0.7359
          },
          {
            "player_id": "124091",
            "player_name": "Bruno Fernandes",
            "team": "POR",
            "opponent": "UZB",
            "line": "2+ Shots",
            "score": 73.29,
            "confidence": 73,
            "tier": "A",
            "reason": "Shots \u03bb 2.60 | Raw shots/m 2.00 | Sample 6 | FIFA World Cup | Shrunk to M prior",
            "sim_prob_pct": 73.29,
            "model_hit_rate": 0.7329
          }
        ],
        "SOT": [
          {
            "player_id": "288896",
            "player_name": "Gon\u00e7alo Ramos",
            "team": "POR",
            "opponent": "UZB",
            "line": "2+ Shots on Goal",
            "score": 83.68,
            "confidence": 84,
            "tier": "A",
            "reason": "SOG \u03bb 3.26 | Raw SOG/m 3.00 | Sample 4 | FIFA World Cup | Shrunk to F prior",
            "sim_prob_pct": 83.68,
            "model_hit_rate": 0.8368
          },
          {
            "player_id": "22774",
            "player_name": "Cristiano Ronaldo",
            "team": "POR",
            "opponent": "UZB",
            "line": "2+ Shots on Goal",
            "score": 69.49,
            "confidence": 69,
            "tier": "B",
            "reason": "SOG \u03bb 2.42 | Raw SOG/m 1.73 | Sample 37 | FIFA World Cup | Shrunk to F prior",
            "sim_prob_pct": 69.49,
            "model_hit_rate": 0.6949
          },
          {
            "player_id": "256115",
            "player_name": "Pedro Neto",
            "team": "POR",
            "opponent": "UZB",
            "line": "1+ Shots on Goal",
            "score": 68.38,
            "confidence": 68,
            "tier": "B",
            "reason": "SOG \u03bb 1.15 | Raw SOG/m 0.80 | Sample 15 | FIFA World Cup | Shrunk to F prior",
            "sim_prob_pct": 68.38,
            "model_hit_rate": 0.6838
          },
          {
            "player_id": "183466",
            "player_name": "Sam\u00fa Costa",
            "team": "POR",
            "opponent": "UZB",
            "line": "1+ Shots on Goal",
            "score": 67.97,
            "confidence": 68,
            "tier": "B",
            "reason": "SOG \u03bb 1.14 | Raw SOG/m 1.00 | Sample 4 | FIFA World Cup | Shrunk to M prior",
            "sim_prob_pct": 67.97,
            "model_hit_rate": 0.6797
          },
          {
            "player_id": "276350",
            "player_name": "Jo\u00e3o F\u00e9lix",
            "team": "POR",
            "opponent": "UZB",
            "line": "2+ Shots on Goal",
            "score": 62.65,
            "confidence": 63,
            "tier": "B",
            "reason": "SOG \u03bb 2.12 | Raw SOG/m 1.51 | Sample 41 | FIFA World Cup | Shrunk to F prior",
            "sim_prob_pct": 62.65,
            "model_hit_rate": 0.6265
          },
          {
            "player_id": "288897",
            "player_name": "Vitinha ",
            "team": "POR",
            "opponent": "UZB",
            "line": "1+ Shots on Goal",
            "score": 61.03,
            "confidence": 61,
            "tier": "B",
            "reason": "SOG \u03bb 0.94 | Raw SOG/m 0.68 | Sample 22 | FIFA World Cup | Shrunk to M prior",
            "sim_prob_pct": 61.03,
            "model_hit_rate": 0.6103
          },
          {
            "player_id": "355061",
            "player_name": "Jo\u00e3o Neves",
            "team": "POR",
            "opponent": "UZB",
            "line": "1+ Shots on Goal",
            "score": 60.85,
            "confidence": 61,
            "tier": "B",
            "reason": "SOG \u03bb 0.94 | Raw SOG/m 0.69 | Sample 16 | FIFA World Cup | Shrunk to M prior",
            "sim_prob_pct": 60.85,
            "model_hit_rate": 0.6085
          },
          {
            "player_id": "274159",
            "player_name": "Francisco Trinc\u00e3o",
            "team": "POR",
            "opponent": "UZB",
            "line": "1+ Shots on Goal",
            "score": 60.48,
            "confidence": 60,
            "tier": "B",
            "reason": "SOG \u03bb 0.93 | Raw SOG/m 0.64 | Sample 50 | FIFA World Cup | Shrunk to F prior",
            "sim_prob_pct": 60.48,
            "model_hit_rate": 0.6048
          },
          {
            "player_id": "216937",
            "player_name": "Eldor Shomurodov",
            "team": "UZB",
            "opponent": "POR",
            "line": "1+ Shots on Goal",
            "score": 58.86,
            "confidence": 59,
            "tier": "B",
            "reason": "SOG \u03bb 0.89 | Raw SOG/m 1.36 | Sample 39 | FIFA World Cup | Shrunk to F prior",
            "sim_prob_pct": 58.86,
            "model_hit_rate": 0.5886
          },
          {
            "player_id": "124091",
            "player_name": "Bruno Fernandes",
            "team": "POR",
            "opponent": "UZB",
            "line": "1+ Shots on Goal",
            "score": 57.43,
            "confidence": 57,
            "tier": "B",
            "reason": "SOG \u03bb 0.85 | Raw SOG/m 0.67 | Sample 6 | FIFA World Cup | Shrunk to M prior",
            "sim_prob_pct": 57.43,
            "model_hit_rate": 0.5743
          }
        ],
        "BTTS": [
          {
            "player_id": "760461-btts",
            "player_name": "Both Teams to Score",
            "team": "POR",
            "opponent": "UZB",
            "line": "BTTS No",
            "score": 51.93,
            "confidence": 52,
            "tier": "C",
            "reason": "Home score 93.1% | Away score 51.6% | xG 2.67-0.73",
            "sim_prob_pct": 51.93,
            "model_hit_rate": 0.5193
          }
        ],
        "1H": [
          {
            "player_id": "760461-1h",
            "player_name": "First Half Goal",
            "team": "POR",
            "opponent": "UZB",
            "line": "1H Over 0.5 Goals",
            "score": 79.06,
            "confidence": 79,
            "tier": "A",
            "reason": "First-half \u03bb 1.56 | 46% goal-time share | Full-match xG 3.40",
            "sim_prob_pct": 79.06,
            "model_hit_rate": 0.7906
          }
        ],
        "1HML": [
          {
            "player_id": "760461-1hml",
            "player_name": "POR",
            "team": "POR",
            "opponent": "UZB",
            "line": "1H Moneyline",
            "score": 59.5,
            "confidence": 60,
            "tier": "B",
            "reason": "1H Poisson 59.5% | 1H xG 1.23-0.33",
            "sim_prob_pct": 59.5,
            "model_hit_rate": 0.595
          }
        ],
        "OU": [
          {
            "player_id": "760461-ou",
            "player_name": "Match Total",
            "team": "POR",
            "opponent": "UZB",
            "line": "Under 3.5 Goals",
            "score": 55.22,
            "confidence": 55,
            "tier": "C",
            "reason": "Total \u03bb 3.40 | Model over 44.1% | Calibrated under 55.2%",
            "sim_prob_pct": 55.22,
            "model_hit_rate": 0.5522,
            "implied_odds": "-135"
          }
        ],
        "ML": [
          {
            "player_id": "760461-ml",
            "player_name": "POR",
            "team": "POR",
            "opponent": "UZB",
            "line": "Moneyline",
            "score": 80.81,
            "confidence": 81,
            "tier": "A",
            "reason": "Calibrated 80.8% | Poisson 78.6% | Market 83.9%",
            "sim_prob_pct": 80.81,
            "model_hit_rate": 0.8081,
            "implied_odds": "-700"
          }
        ]
      }
    },
    {
      "game_id": "760458",
      "matchup": "GHA @ ENG",
      "time": "FIFA World Cup | Scheduled",
      "top_signals": [
        {
          "market": "SOT",
          "player_name": "Harry Kane",
          "line": "2+ Shots on Goal",
          "score": 87.64,
          "confidence": 88,
          "tier": "A",
          "player_id": "142200"
        },
        {
          "market": "SHOTS",
          "player_name": "Marcus Rashford",
          "line": "2+ Shots",
          "score": 98.04,
          "confidence": 98,
          "tier": "A",
          "player_id": "230945"
        },
        {
          "market": "BTTS",
          "player_name": "Both Teams to Score",
          "line": "BTTS No",
          "score": 50.78,
          "confidence": 51,
          "tier": "C",
          "player_id": "760458-btts"
        }
      ],
      "markets": {
        "GS": [
          {
            "player_id": "142200",
            "player_name": "Harry Kane",
            "team": "ENG",
            "opponent": "GHA",
            "line": "Anytime Goal",
            "score": 84.45,
            "confidence": 84,
            "tier": "A",
            "reason": "Goal \u03bb 1.86 | Raw G/m 1.36 | Team xG 2.51 | Sample 47 | FIFA World Cup | Shrunk to F prior",
            "sim_prob_pct": 84.45,
            "model_hit_rate": 0.8445
          },
          {
            "player_id": "268782",
            "player_name": "Anthony Gordon",
            "team": "ENG",
            "opponent": "GHA",
            "line": "Anytime Goal",
            "score": 70.73,
            "confidence": 71,
            "tier": "B",
            "reason": "Goal \u03bb 1.23 | Raw G/m 1.00 | Team xG 2.51 | Sample 12 | FIFA World Cup | Shrunk to F prior",
            "sim_prob_pct": 70.73,
            "model_hit_rate": 0.7073
          },
          {
            "player_id": "180639",
            "player_name": "Ivan Toney",
            "team": "ENG",
            "opponent": "GHA",
            "line": "Anytime Goal",
            "score": 69.59,
            "confidence": 70,
            "tier": "B",
            "reason": "Goal \u03bb 1.19 | Raw G/m 0.87 | Team xG 2.51 | Sample 39 | FIFA World Cup | Shrunk to F prior",
            "sim_prob_pct": 69.59,
            "model_hit_rate": 0.6959
          },
          {
            "player_id": "230945",
            "player_name": "Marcus Rashford",
            "team": "ENG",
            "opponent": "GHA",
            "line": "Anytime Goal",
            "score": 57.92,
            "confidence": 58,
            "tier": "B",
            "reason": "Goal \u03bb 0.87 | Raw G/m 0.70 | Team xG 2.51 | Sample 10 | FIFA World Cup | Shrunk to F prior",
            "sim_prob_pct": 57.92,
            "model_hit_rate": 0.5792
          },
          {
            "player_id": "198825",
            "player_name": "Ollie Watkins",
            "team": "ENG",
            "opponent": "GHA",
            "line": "Anytime Goal",
            "score": 50.4,
            "confidence": 50,
            "tier": "C",
            "reason": "Goal \u03bb 0.70 | Raw G/m 0.55 | Team xG 2.51 | Sample 11 | FIFA World Cup | Shrunk to F prior",
            "sim_prob_pct": 50.4,
            "model_hit_rate": 0.504
          },
          {
            "player_id": "293236",
            "player_name": "Noni Madueke",
            "team": "ENG",
            "opponent": "GHA",
            "line": "Anytime Goal",
            "score": 42.81,
            "confidence": 43,
            "tier": "C",
            "reason": "Goal \u03bb 0.56 | Raw G/m 0.42 | Team xG 2.51 | Sample 12 | FIFA World Cup | Shrunk to F prior",
            "sim_prob_pct": 42.81,
            "model_hit_rate": 0.4281
          },
          {
            "player_id": "280555",
            "player_name": "Bukayo Saka",
            "team": "ENG",
            "opponent": "GHA",
            "line": "Anytime Goal",
            "score": 36.83,
            "confidence": 37,
            "tier": "C",
            "reason": "Goal \u03bb 0.46 | Raw G/m 0.33 | Team xG 2.51 | Sample 9 | FIFA World Cup | Shrunk to F prior",
            "sim_prob_pct": 36.83,
            "model_hit_rate": 0.3683
          },
          {
            "player_id": "291281",
            "player_name": "Jude Bellingham",
            "team": "ENG",
            "opponent": "GHA",
            "line": "Anytime Goal",
            "score": 34.99,
            "confidence": 35,
            "tier": "C",
            "reason": "Goal \u03bb 0.43 | Raw G/m 0.38 | Team xG 2.51 | Sample 8 | FIFA World Cup | Shrunk to M prior",
            "sim_prob_pct": 34.99,
            "model_hit_rate": 0.3499
          },
          {
            "player_id": "265653",
            "player_name": "Morgan Rogers",
            "team": "ENG",
            "opponent": "GHA",
            "line": "Anytime Goal",
            "score": 30.62,
            "confidence": 31,
            "tier": "C",
            "reason": "Goal \u03bb 0.37 | Raw G/m 0.25 | Team xG 2.51 | Sample 16 | FIFA World Cup | Shrunk to F prior",
            "sim_prob_pct": 30.62,
            "model_hit_rate": 0.3062
          },
          {
            "player_id": "273292",
            "player_name": "Antoine Semenyo",
            "team": "GHA",
            "opponent": "ENG",
            "line": "Anytime Goal",
            "score": 22.58,
            "confidence": 23,
            "tier": "C",
            "reason": "Goal \u03bb 0.26 | Raw G/m 0.43 | Team xG 0.77 | Sample 7 | FIFA World Cup | Shrunk to F prior",
            "sim_prob_pct": 22.58,
            "model_hit_rate": 0.2258
          }
        ],
        "AST": [
          {
            "player_id": "230945",
            "player_name": "Marcus Rashford",
            "team": "ENG",
            "opponent": "GHA",
            "line": "Assist",
            "score": 38.61,
            "confidence": 39,
            "tier": "C",
            "reason": "Assist \u03bb 0.49 | Raw A/m 0.40 | Team xG 2.51 | Sample 10 | FIFA World Cup | Shrunk to F prior",
            "sim_prob_pct": 38.61,
            "model_hit_rate": 0.3861
          },
          {
            "player_id": "268782",
            "player_name": "Anthony Gordon",
            "team": "ENG",
            "opponent": "GHA",
            "line": "Assist",
            "score": 34.49,
            "confidence": 34,
            "tier": "C",
            "reason": "Assist \u03bb 0.42 | Raw A/m 0.33 | Team xG 2.51 | Sample 12 | FIFA World Cup | Shrunk to F prior",
            "sim_prob_pct": 34.49,
            "model_hit_rate": 0.3449
          },
          {
            "player_id": "265653",
            "player_name": "Morgan Rogers",
            "team": "ENG",
            "opponent": "GHA",
            "line": "Assist",
            "score": 33.6,
            "confidence": 34,
            "tier": "C",
            "reason": "Assist \u03bb 0.41 | Raw A/m 0.31 | Team xG 2.51 | Sample 16 | FIFA World Cup | Shrunk to F prior",
            "sim_prob_pct": 33.6,
            "model_hit_rate": 0.336
          },
          {
            "player_id": "280555",
            "player_name": "Bukayo Saka",
            "team": "ENG",
            "opponent": "GHA",
            "line": "Assist",
            "score": 33.57,
            "confidence": 34,
            "tier": "C",
            "reason": "Assist \u03bb 0.41 | Raw A/m 0.33 | Team xG 2.51 | Sample 9 | FIFA World Cup | Shrunk to F prior",
            "sim_prob_pct": 33.57,
            "model_hit_rate": 0.3357
          },
          {
            "player_id": "180639",
            "player_name": "Ivan Toney",
            "team": "ENG",
            "opponent": "GHA",
            "line": "Assist",
            "score": 29.96,
            "confidence": 30,
            "tier": "C",
            "reason": "Assist \u03bb 0.36 | Raw A/m 0.26 | Team xG 2.51 | Sample 39 | FIFA World Cup | Shrunk to F prior",
            "sim_prob_pct": 29.96,
            "model_hit_rate": 0.2996
          },
          {
            "player_id": "251400",
            "player_name": "Eberechi Eze",
            "team": "ENG",
            "opponent": "GHA",
            "line": "Assist",
            "score": 28.32,
            "confidence": 28,
            "tier": "C",
            "reason": "Assist \u03bb 0.33 | Raw A/m 0.25 | Team xG 2.51 | Sample 12 | FIFA World Cup | Shrunk to M prior",
            "sim_prob_pct": 28.32,
            "model_hit_rate": 0.2832
          },
          {
            "player_id": "238262",
            "player_name": "Declan Rice",
            "team": "ENG",
            "opponent": "GHA",
            "line": "Assist",
            "score": 26.81,
            "confidence": 27,
            "tier": "C",
            "reason": "Assist \u03bb 0.31 | Raw A/m 0.23 | Team xG 2.51 | Sample 13 | FIFA World Cup | Shrunk to M prior",
            "sim_prob_pct": 26.81,
            "model_hit_rate": 0.2681
          },
          {
            "player_id": "198138",
            "player_name": "Dan Burn",
            "team": "ENG",
            "opponent": "GHA",
            "line": "Assist",
            "score": 26.44,
            "confidence": 26,
            "tier": "C",
            "reason": "Assist \u03bb 0.31 | Raw A/m 0.25 | Team xG 2.51 | Sample 12 | FIFA World Cup | Shrunk to D prior",
            "sim_prob_pct": 26.44,
            "model_hit_rate": 0.2644
          },
          {
            "player_id": "328464",
            "player_name": "Nico O'Reilly",
            "team": "ENG",
            "opponent": "GHA",
            "line": "Assist",
            "score": 25.02,
            "confidence": 25,
            "tier": "C",
            "reason": "Assist \u03bb 0.29 | Raw A/m 0.23 | Team xG 2.51 | Sample 13 | FIFA World Cup | Shrunk to D prior",
            "sim_prob_pct": 25.02,
            "model_hit_rate": 0.2502
          },
          {
            "player_id": "238472",
            "player_name": "Elliot Anderson",
            "team": "ENG",
            "opponent": "GHA",
            "line": "Assist",
            "score": 22.45,
            "confidence": 22,
            "tier": "C",
            "reason": "Assist \u03bb 0.25 | Raw A/m 0.18 | Team xG 2.51 | Sample 11 | FIFA World Cup | Shrunk to M prior",
            "sim_prob_pct": 22.45,
            "model_hit_rate": 0.2245
          }
        ],
        "SHOTS": [
          {
            "player_id": "142200",
            "player_name": "Harry Kane",
            "team": "ENG",
            "opponent": "GHA",
            "line": "2+ Shots",
            "score": 98.62,
            "confidence": 99,
            "tier": "A",
            "reason": "Shots \u03bb 6.27 | Raw shots/m 4.47 | Sample 47 | FIFA World Cup | Shrunk to F prior",
            "sim_prob_pct": 98.62,
            "model_hit_rate": 0.9862
          },
          {
            "player_id": "230945",
            "player_name": "Marcus Rashford",
            "team": "ENG",
            "opponent": "GHA",
            "line": "2+ Shots",
            "score": 98.04,
            "confidence": 98,
            "tier": "A",
            "reason": "Shots \u03bb 5.86 | Raw shots/m 4.50 | Sample 10 | FIFA World Cup | Shrunk to F prior",
            "sim_prob_pct": 98.04,
            "model_hit_rate": 0.9804
          },
          {
            "player_id": "280555",
            "player_name": "Bukayo Saka",
            "team": "ENG",
            "opponent": "GHA",
            "line": "2+ Shots",
            "score": 95.33,
            "confidence": 95,
            "tier": "A",
            "reason": "Shots \u03bb 4.83 | Raw shots/m 3.67 | Sample 9 | FIFA World Cup | Shrunk to F prior",
            "sim_prob_pct": 95.33,
            "model_hit_rate": 0.9533
          },
          {
            "player_id": "268782",
            "player_name": "Anthony Gordon",
            "team": "ENG",
            "opponent": "GHA",
            "line": "2+ Shots",
            "score": 93.41,
            "confidence": 93,
            "tier": "A",
            "reason": "Shots \u03bb 4.41 | Raw shots/m 3.25 | Sample 12 | FIFA World Cup | Shrunk to F prior",
            "sim_prob_pct": 93.41,
            "model_hit_rate": 0.9341
          },
          {
            "player_id": "198825",
            "player_name": "Ollie Watkins",
            "team": "ENG",
            "opponent": "GHA",
            "line": "2+ Shots",
            "score": 91.44,
            "confidence": 91,
            "tier": "A",
            "reason": "Shots \u03bb 4.08 | Raw shots/m 3.00 | Sample 11 | FIFA World Cup | Shrunk to F prior",
            "sim_prob_pct": 91.44,
            "model_hit_rate": 0.9144
          },
          {
            "player_id": "180639",
            "player_name": "Ivan Toney",
            "team": "ENG",
            "opponent": "GHA",
            "line": "2+ Shots",
            "score": 91.28,
            "confidence": 91,
            "tier": "A",
            "reason": "Shots \u03bb 4.06 | Raw shots/m 2.87 | Sample 39 | FIFA World Cup | Shrunk to F prior",
            "sim_prob_pct": 91.28,
            "model_hit_rate": 0.9128
          },
          {
            "player_id": "291281",
            "player_name": "Jude Bellingham",
            "team": "ENG",
            "opponent": "GHA",
            "line": "2+ Shots",
            "score": 88.01,
            "confidence": 88,
            "tier": "A",
            "reason": "Shots \u03bb 3.66 | Raw shots/m 2.88 | Sample 8 | FIFA World Cup | Shrunk to M prior",
            "sim_prob_pct": 88.01,
            "model_hit_rate": 0.8801
          },
          {
            "player_id": "265653",
            "player_name": "Morgan Rogers",
            "team": "ENG",
            "opponent": "GHA",
            "line": "2+ Shots",
            "score": 87.31,
            "confidence": 87,
            "tier": "A",
            "reason": "Shots \u03bb 3.59 | Raw shots/m 2.56 | Sample 16 | FIFA World Cup | Shrunk to F prior",
            "sim_prob_pct": 87.31,
            "model_hit_rate": 0.8731
          },
          {
            "player_id": "293236",
            "player_name": "Noni Madueke",
            "team": "ENG",
            "opponent": "GHA",
            "line": "2+ Shots",
            "score": 87.31,
            "confidence": 87,
            "tier": "A",
            "reason": "Shots \u03bb 3.59 | Raw shots/m 2.58 | Sample 12 | FIFA World Cup | Shrunk to F prior",
            "sim_prob_pct": 87.31,
            "model_hit_rate": 0.8731
          },
          {
            "player_id": "251400",
            "player_name": "Eberechi Eze",
            "team": "ENG",
            "opponent": "GHA",
            "line": "2+ Shots",
            "score": 85.7,
            "confidence": 86,
            "tier": "A",
            "reason": "Shots \u03bb 3.43 | Raw shots/m 2.58 | Sample 12 | FIFA World Cup | Shrunk to M prior",
            "sim_prob_pct": 85.7,
            "model_hit_rate": 0.857
          }
        ],
        "SOT": [
          {
            "player_id": "142200",
            "player_name": "Harry Kane",
            "team": "ENG",
            "opponent": "GHA",
            "line": "2+ Shots on Goal",
            "score": 87.64,
            "confidence": 88,
            "tier": "A",
            "reason": "SOG \u03bb 3.62 | Raw SOG/m 2.60 | Sample 47 | FIFA World Cup | Shrunk to F prior",
            "sim_prob_pct": 87.64,
            "model_hit_rate": 0.8764
          },
          {
            "player_id": "230945",
            "player_name": "Marcus Rashford",
            "team": "ENG",
            "opponent": "GHA",
            "line": "2+ Shots on Goal",
            "score": 70.62,
            "confidence": 71,
            "tier": "B",
            "reason": "SOG \u03bb 2.47 | Raw SOG/m 1.90 | Sample 10 | FIFA World Cup | Shrunk to F prior",
            "sim_prob_pct": 70.62,
            "model_hit_rate": 0.7062
          },
          {
            "player_id": "328464",
            "player_name": "Nico O'Reilly",
            "team": "ENG",
            "opponent": "GHA",
            "line": "1+ Shots on Goal",
            "score": 69.12,
            "confidence": 69,
            "tier": "B",
            "reason": "SOG \u03bb 1.17 | Raw SOG/m 0.92 | Sample 13 | FIFA World Cup | Shrunk to D prior",
            "sim_prob_pct": 69.12,
            "model_hit_rate": 0.6912
          },
          {
            "player_id": "280555",
            "player_name": "Bukayo Saka",
            "team": "ENG",
            "opponent": "GHA",
            "line": "2+ Shots on Goal",
            "score": 66.95,
            "confidence": 67,
            "tier": "B",
            "reason": "SOG \u03bb 2.30 | Raw SOG/m 1.78 | Sample 9 | FIFA World Cup | Shrunk to F prior",
            "sim_prob_pct": 66.95,
            "model_hit_rate": 0.6695
          },
          {
            "player_id": "268782",
            "player_name": "Anthony Gordon",
            "team": "ENG",
            "opponent": "GHA",
            "line": "2+ Shots on Goal",
            "score": 64.99,
            "confidence": 65,
            "tier": "B",
            "reason": "SOG \u03bb 2.22 | Raw SOG/m 1.67 | Sample 12 | FIFA World Cup | Shrunk to F prior",
            "sim_prob_pct": 64.99,
            "model_hit_rate": 0.6499
          },
          {
            "player_id": "291281",
            "player_name": "Jude Bellingham",
            "team": "ENG",
            "opponent": "GHA",
            "line": "1+ Shots on Goal",
            "score": 62.1,
            "confidence": 62,
            "tier": "B",
            "reason": "SOG \u03bb 0.97 | Raw SOG/m 0.75 | Sample 8 | FIFA World Cup | Shrunk to M prior",
            "sim_prob_pct": 62.1,
            "model_hit_rate": 0.621
          },
          {
            "player_id": "198825",
            "player_name": "Ollie Watkins",
            "team": "ENG",
            "opponent": "GHA",
            "line": "2+ Shots on Goal",
            "score": 60.94,
            "confidence": 61,
            "tier": "B",
            "reason": "SOG \u03bb 2.06 | Raw SOG/m 1.55 | Sample 11 | FIFA World Cup | Shrunk to F prior",
            "sim_prob_pct": 60.94,
            "model_hit_rate": 0.6094
          },
          {
            "player_id": "180639",
            "player_name": "Ivan Toney",
            "team": "ENG",
            "opponent": "GHA",
            "line": "2+ Shots on Goal",
            "score": 60.81,
            "confidence": 61,
            "tier": "B",
            "reason": "SOG \u03bb 2.05 | Raw SOG/m 1.46 | Sample 39 | FIFA World Cup | Shrunk to F prior",
            "sim_prob_pct": 60.81,
            "model_hit_rate": 0.6081
          },
          {
            "player_id": "198138",
            "player_name": "Dan Burn",
            "team": "ENG",
            "opponent": "GHA",
            "line": "1+ Shots on Goal",
            "score": 57.21,
            "confidence": 57,
            "tier": "B",
            "reason": "SOG \u03bb 0.85 | Raw SOG/m 0.67 | Sample 12 | FIFA World Cup | Shrunk to D prior",
            "sim_prob_pct": 57.21,
            "model_hit_rate": 0.5721
          },
          {
            "player_id": "251400",
            "player_name": "Eberechi Eze",
            "team": "ENG",
            "opponent": "GHA",
            "line": "1+ Shots on Goal",
            "score": 49.99,
            "confidence": 50,
            "tier": "C",
            "reason": "SOG \u03bb 0.69 | Raw SOG/m 0.50 | Sample 12 | FIFA World Cup | Shrunk to M prior",
            "sim_prob_pct": 49.99,
            "model_hit_rate": 0.4999
          }
        ],
        "BTTS": [
          {
            "player_id": "760458-btts",
            "player_name": "Both Teams to Score",
            "team": "ENG",
            "opponent": "GHA",
            "line": "BTTS No",
            "score": 50.78,
            "confidence": 51,
            "tier": "C",
            "reason": "Home score 91.9% | Away score 53.6% | xG 2.51-0.77",
            "sim_prob_pct": 50.78,
            "model_hit_rate": 0.5078
          }
        ],
        "1H": [
          {
            "player_id": "760458-1h",
            "player_name": "First Half Goal",
            "team": "ENG",
            "opponent": "GHA",
            "line": "1H Over 0.5 Goals",
            "score": 77.84,
            "confidence": 78,
            "tier": "A",
            "reason": "First-half \u03bb 1.51 | 46% goal-time share | Full-match xG 3.28",
            "sim_prob_pct": 77.84,
            "model_hit_rate": 0.7784
          }
        ],
        "1HML": [
          {
            "player_id": "760458-1hml",
            "player_name": "ENG",
            "team": "ENG",
            "opponent": "GHA",
            "line": "1H Moneyline",
            "score": 56.55,
            "confidence": 57,
            "tier": "B",
            "reason": "1H Poisson 56.5% | 1H xG 1.15-0.35",
            "sim_prob_pct": 56.55,
            "model_hit_rate": 0.5655
          }
        ],
        "OU": [
          {
            "player_id": "760458-ou",
            "player_name": "Match Total",
            "team": "ENG",
            "opponent": "GHA",
            "line": "Under 3.5 Goals",
            "score": 58.97,
            "confidence": 59,
            "tier": "B",
            "reason": "Total \u03bb 3.28 | Model over 41.4% | Calibrated under 59.0%",
            "sim_prob_pct": 58.97,
            "model_hit_rate": 0.5897,
            "implied_odds": "-170"
          }
        ],
        "ML": [
          {
            "player_id": "760458-ml",
            "player_name": "ENG",
            "team": "ENG",
            "opponent": "GHA",
            "line": "Moneyline",
            "score": 77.77,
            "confidence": 78,
            "tier": "A",
            "reason": "Calibrated 77.8% | Poisson 75.3% | Market 81.2%",
            "sim_prob_pct": 77.77,
            "model_hit_rate": 0.7777,
            "implied_odds": "-550"
          }
        ]
      }
    },
    {
      "game_id": "760460",
      "matchup": "CRO @ PAN",
      "time": "FIFA World Cup | Scheduled",
      "top_signals": [
        {
          "market": "SOT",
          "player_name": "Luka Sucic",
          "line": "1+ Shots on Goal",
          "score": 69.18,
          "confidence": 69,
          "tier": "B",
          "player_id": "306263"
        },
        {
          "market": "SHOTS",
          "player_name": "Petar Musa",
          "line": "2+ Shots",
          "score": 94.18,
          "confidence": 94,
          "tier": "A",
          "player_id": "277128"
        },
        {
          "market": "BTTS",
          "player_name": "Both Teams to Score",
          "line": "BTTS Yes",
          "score": 57.57,
          "confidence": 58,
          "tier": "B",
          "player_id": "760460-btts"
        }
      ],
      "markets": {
        "GS": [
          {
            "player_id": "277128",
            "player_name": "Petar Musa",
            "team": "CRO",
            "opponent": "PAN",
            "line": "Anytime Goal",
            "score": 63.45,
            "confidence": 63,
            "tier": "B",
            "reason": "Goal \u03bb 1.01 | Raw G/m 0.93 | Team xG 2.05 | Sample 14 | FIFA World Cup | Shrunk to F prior",
            "sim_prob_pct": 63.45,
            "model_hit_rate": 0.6345
          },
          {
            "player_id": "189668",
            "player_name": "Mario Pasalic",
            "team": "CRO",
            "opponent": "PAN",
            "line": "Anytime Goal",
            "score": 54.58,
            "confidence": 55,
            "tier": "C",
            "reason": "Goal \u03bb 0.79 | Raw G/m 0.80 | Team xG 2.05 | Sample 10 | FIFA World Cup | Shrunk to M prior",
            "sim_prob_pct": 54.58,
            "model_hit_rate": 0.5458
          },
          {
            "player_id": "310883",
            "player_name": "Igor Matanovic",
            "team": "CRO",
            "opponent": "PAN",
            "line": "Anytime Goal",
            "score": 51.22,
            "confidence": 51,
            "tier": "C",
            "reason": "Goal \u03bb 0.72 | Raw G/m 0.62 | Team xG 2.05 | Sample 26 | FIFA World Cup | Shrunk to F prior",
            "sim_prob_pct": 51.22,
            "model_hit_rate": 0.5122
          },
          {
            "player_id": "207288",
            "player_name": "Ante Budimir",
            "team": "CRO",
            "opponent": "PAN",
            "line": "Anytime Goal",
            "score": 50.45,
            "confidence": 50,
            "tier": "C",
            "reason": "Goal \u03bb 0.70 | Raw G/m 1.00 | Team xG 2.05 | Sample 2 | FIFA World Cup | Shrunk to F prior",
            "sim_prob_pct": 50.45,
            "model_hit_rate": 0.5045
          },
          {
            "player_id": "139520",
            "player_name": "Andrej Kramaric",
            "team": "CRO",
            "opponent": "PAN",
            "line": "Anytime Goal",
            "score": 44.76,
            "confidence": 45,
            "tier": "C",
            "reason": "Goal \u03bb 0.59 | Raw G/m 0.50 | Team xG 2.05 | Sample 30 | FIFA World Cup | Shrunk to F prior",
            "sim_prob_pct": 44.76,
            "model_hit_rate": 0.4476
          },
          {
            "player_id": "338232",
            "player_name": "Toni Fruk",
            "team": "CRO",
            "opponent": "PAN",
            "line": "Anytime Goal",
            "score": 39.59,
            "confidence": 40,
            "tier": "C",
            "reason": "Goal \u03bb 0.50 | Raw G/m 0.50 | Team xG 2.05 | Sample 10 | FIFA World Cup | Shrunk to M prior",
            "sim_prob_pct": 39.59,
            "model_hit_rate": 0.3959
          },
          {
            "player_id": "311475",
            "player_name": "Martin Baturina",
            "team": "CRO",
            "opponent": "PAN",
            "line": "Anytime Goal",
            "score": 36.45,
            "confidence": 36,
            "tier": "C",
            "reason": "Goal \u03bb 0.45 | Raw G/m 0.50 | Team xG 2.05 | Sample 6 | FIFA World Cup | Shrunk to M prior",
            "sim_prob_pct": 36.45,
            "model_hit_rate": 0.3645
          },
          {
            "player_id": "103485",
            "player_name": "Ivan Perisic",
            "team": "CRO",
            "opponent": "PAN",
            "line": "Anytime Goal",
            "score": 24.37,
            "confidence": 24,
            "tier": "C",
            "reason": "Goal \u03bb 0.28 | Raw G/m 0.21 | Team xG 2.05 | Sample 14 | FIFA World Cup | Shrunk to F prior",
            "sim_prob_pct": 24.37,
            "model_hit_rate": 0.2437
          },
          {
            "player_id": "324270",
            "player_name": "Marco Pasalic",
            "team": "CRO",
            "opponent": "PAN",
            "line": "Anytime Goal",
            "score": 23.67,
            "confidence": 24,
            "tier": "C",
            "reason": "Goal \u03bb 0.27 | Raw G/m 0.20 | Team xG 2.05 | Sample 10 | FIFA World Cup | Shrunk to F prior",
            "sim_prob_pct": 23.67,
            "model_hit_rate": 0.2367
          },
          {
            "player_id": "306263",
            "player_name": "Luka Sucic",
            "team": "CRO",
            "opponent": "PAN",
            "line": "Anytime Goal",
            "score": 23.5,
            "confidence": 24,
            "tier": "C",
            "reason": "Goal \u03bb 0.27 | Raw G/m 0.33 | Team xG 2.05 | Sample 3 | FIFA World Cup | Shrunk to M prior",
            "sim_prob_pct": 23.5,
            "model_hit_rate": 0.235
          }
        ],
        "AST": [
          {
            "player_id": "306263",
            "player_name": "Luka Sucic",
            "team": "CRO",
            "opponent": "PAN",
            "line": "Assist",
            "score": 40.01,
            "confidence": 40,
            "tier": "C",
            "reason": "Assist \u03bb 0.51 | Raw A/m 0.67 | Team xG 2.05 | Sample 3 | FIFA World Cup | Shrunk to M prior",
            "sim_prob_pct": 40.01,
            "model_hit_rate": 0.4001
          },
          {
            "player_id": "206378",
            "player_name": "Nikola Vlasic",
            "team": "CRO",
            "opponent": "PAN",
            "line": "Assist",
            "score": 35.47,
            "confidence": 35,
            "tier": "C",
            "reason": "Assist \u03bb 0.44 | Raw A/m 0.50 | Team xG 2.05 | Sample 4 | FIFA World Cup | Shrunk to M prior",
            "sim_prob_pct": 35.47,
            "model_hit_rate": 0.3547
          },
          {
            "player_id": "103485",
            "player_name": "Ivan Perisic",
            "team": "CRO",
            "opponent": "PAN",
            "line": "Assist",
            "score": 27.49,
            "confidence": 27,
            "tier": "C",
            "reason": "Assist \u03bb 0.32 | Raw A/m 0.29 | Team xG 2.05 | Sample 14 | FIFA World Cup | Shrunk to F prior",
            "sim_prob_pct": 27.49,
            "model_hit_rate": 0.2749
          },
          {
            "player_id": "139520",
            "player_name": "Andrej Kramaric",
            "team": "CRO",
            "opponent": "PAN",
            "line": "Assist",
            "score": 27.05,
            "confidence": 27,
            "tier": "C",
            "reason": "Assist \u03bb 0.32 | Raw A/m 0.27 | Team xG 2.05 | Sample 30 | FIFA World Cup | Shrunk to F prior",
            "sim_prob_pct": 27.05,
            "model_hit_rate": 0.2705
          },
          {
            "player_id": "341494",
            "player_name": "Petar Sucic",
            "team": "CRO",
            "opponent": "PAN",
            "line": "Assist",
            "score": 26.46,
            "confidence": 26,
            "tier": "C",
            "reason": "Assist \u03bb 0.31 | Raw A/m 0.27 | Team xG 2.05 | Sample 11 | FIFA World Cup | Shrunk to M prior",
            "sim_prob_pct": 26.46,
            "model_hit_rate": 0.2646
          },
          {
            "player_id": "189668",
            "player_name": "Mario Pasalic",
            "team": "CRO",
            "opponent": "PAN",
            "line": "Assist",
            "score": 21.01,
            "confidence": 21,
            "tier": "C",
            "reason": "Assist \u03bb 0.24 | Raw A/m 0.20 | Team xG 2.05 | Sample 10 | FIFA World Cup | Shrunk to M prior",
            "sim_prob_pct": 21.01,
            "model_hit_rate": 0.2101
          },
          {
            "player_id": "324270",
            "player_name": "Marco Pasalic",
            "team": "CRO",
            "opponent": "PAN",
            "line": "Assist",
            "score": 20.56,
            "confidence": 21,
            "tier": "C",
            "reason": "Assist \u03bb 0.23 | Raw A/m 0.20 | Team xG 2.05 | Sample 10 | FIFA World Cup | Shrunk to F prior",
            "sim_prob_pct": 20.56,
            "model_hit_rate": 0.2056
          },
          {
            "player_id": "138183",
            "player_name": "\u00c9ric Davis",
            "team": "PAN",
            "opponent": "CRO",
            "line": "Assist",
            "score": 19.26,
            "confidence": 19,
            "tier": "C",
            "reason": "Assist \u03bb 0.21 | Raw A/m 1.00 | Team xG 1.08 | Sample 1 | FIFA World Cup | Shrunk to D prior",
            "sim_prob_pct": 19.26,
            "model_hit_rate": 0.1926
          },
          {
            "player_id": "219508",
            "player_name": "Adalberto Carrasquilla",
            "team": "PAN",
            "opponent": "CRO",
            "line": "Assist",
            "score": 18.89,
            "confidence": 19,
            "tier": "C",
            "reason": "Assist \u03bb 0.21 | Raw A/m 0.50 | Team xG 1.08 | Sample 2 | FIFA World Cup | Shrunk to M prior",
            "sim_prob_pct": 18.89,
            "model_hit_rate": 0.1889
          },
          {
            "player_id": "311475",
            "player_name": "Martin Baturina",
            "team": "CRO",
            "opponent": "PAN",
            "line": "Assist",
            "score": 18.4,
            "confidence": 18,
            "tier": "C",
            "reason": "Assist \u03bb 0.20 | Raw A/m 0.17 | Team xG 2.05 | Sample 6 | FIFA World Cup | Shrunk to M prior",
            "sim_prob_pct": 18.4,
            "model_hit_rate": 0.184
          }
        ],
        "SHOTS": [
          {
            "player_id": "277128",
            "player_name": "Petar Musa",
            "team": "CRO",
            "opponent": "PAN",
            "line": "2+ Shots",
            "score": 94.18,
            "confidence": 94,
            "tier": "A",
            "reason": "Shots \u03bb 4.56 | Raw shots/m 3.93 | Sample 14 | FIFA World Cup | Shrunk to F prior",
            "sim_prob_pct": 94.18,
            "model_hit_rate": 0.9418
          },
          {
            "player_id": "306263",
            "player_name": "Luka Sucic",
            "team": "CRO",
            "opponent": "PAN",
            "line": "2+ Shots",
            "score": 92.96,
            "confidence": 93,
            "tier": "A",
            "reason": "Shots \u03bb 4.33 | Raw shots/m 5.00 | Sample 3 | FIFA World Cup | Shrunk to M prior",
            "sim_prob_pct": 92.96,
            "model_hit_rate": 0.9296
          },
          {
            "player_id": "310883",
            "player_name": "Igor Matanovic",
            "team": "CRO",
            "opponent": "PAN",
            "line": "2+ Shots",
            "score": 92.17,
            "confidence": 92,
            "tier": "A",
            "reason": "Shots \u03bb 4.19 | Raw shots/m 3.50 | Sample 26 | FIFA World Cup | Shrunk to F prior",
            "sim_prob_pct": 92.17,
            "model_hit_rate": 0.9217
          },
          {
            "player_id": "207288",
            "player_name": "Ante Budimir",
            "team": "CRO",
            "opponent": "PAN",
            "line": "2+ Shots",
            "score": 88.46,
            "confidence": 88,
            "tier": "A",
            "reason": "Shots \u03bb 3.71 | Raw shots/m 4.00 | Sample 2 | FIFA World Cup | Shrunk to F prior",
            "sim_prob_pct": 88.46,
            "model_hit_rate": 0.8846
          },
          {
            "player_id": "338232",
            "player_name": "Toni Fruk",
            "team": "CRO",
            "opponent": "PAN",
            "line": "2+ Shots",
            "score": 86.97,
            "confidence": 87,
            "tier": "A",
            "reason": "Shots \u03bb 3.55 | Raw shots/m 3.20 | Sample 10 | FIFA World Cup | Shrunk to M prior",
            "sim_prob_pct": 86.97,
            "model_hit_rate": 0.8697
          },
          {
            "player_id": "189668",
            "player_name": "Mario Pasalic",
            "team": "CRO",
            "opponent": "PAN",
            "line": "2+ Shots",
            "score": 82.11,
            "confidence": 82,
            "tier": "A",
            "reason": "Shots \u03bb 3.14 | Raw shots/m 2.80 | Sample 10 | FIFA World Cup | Shrunk to M prior",
            "sim_prob_pct": 82.11,
            "model_hit_rate": 0.8211
          },
          {
            "player_id": "139520",
            "player_name": "Andrej Kramaric",
            "team": "CRO",
            "opponent": "PAN",
            "line": "2+ Shots",
            "score": 79.11,
            "confidence": 79,
            "tier": "A",
            "reason": "Shots \u03bb 2.94 | Raw shots/m 2.40 | Sample 30 | FIFA World Cup | Shrunk to F prior",
            "sim_prob_pct": 79.11,
            "model_hit_rate": 0.7911
          },
          {
            "player_id": "364962",
            "player_name": "Luka Vuskovic",
            "team": "CRO",
            "opponent": "PAN",
            "line": "1+ Shots",
            "score": 75.74,
            "confidence": 76,
            "tier": "A",
            "reason": "Shots \u03bb 1.42 | Raw shots/m 1.18 | Sample 33 | FIFA World Cup | Shrunk to D prior",
            "sim_prob_pct": 75.74,
            "model_hit_rate": 0.7574
          },
          {
            "player_id": "238929",
            "player_name": "Kristijan Jakic",
            "team": "CRO",
            "opponent": "PAN",
            "line": "1+ Shots",
            "score": 70.13,
            "confidence": 70,
            "tier": "B",
            "reason": "Shots \u03bb 1.21 | Raw shots/m 0.95 | Sample 20 | FIFA World Cup | Shrunk to M prior",
            "sim_prob_pct": 70.13,
            "model_hit_rate": 0.7013
          },
          {
            "player_id": "267996",
            "player_name": "Jos\u00e9 Fajardo",
            "team": "PAN",
            "opponent": "CRO",
            "line": "2+ Shots",
            "score": 67.81,
            "confidence": 68,
            "tier": "B",
            "reason": "Shots \u03bb 2.34 | Raw shots/m 3.55 | Sample 11 | FIFA World Cup | Shrunk to F prior",
            "sim_prob_pct": 67.81,
            "model_hit_rate": 0.6781
          }
        ],
        "SOT": [
          {
            "player_id": "306263",
            "player_name": "Luka Sucic",
            "team": "CRO",
            "opponent": "PAN",
            "line": "1+ Shots on Goal",
            "score": 69.18,
            "confidence": 69,
            "tier": "B",
            "reason": "SOG \u03bb 1.18 | Raw SOG/m 1.33 | Sample 3 | FIFA World Cup | Shrunk to M prior",
            "sim_prob_pct": 69.18,
            "model_hit_rate": 0.6918
          },
          {
            "player_id": "195326",
            "player_name": "Ismael D\u00edaz",
            "team": "PAN",
            "opponent": "CRO",
            "line": "1+ Shots on Goal",
            "score": 69.09,
            "confidence": 69,
            "tier": "B",
            "reason": "SOG \u03bb 1.17 | Raw SOG/m 2.50 | Sample 2 | FIFA World Cup | Shrunk to F prior",
            "sim_prob_pct": 69.09,
            "model_hit_rate": 0.6909
          },
          {
            "player_id": "311475",
            "player_name": "Martin Baturina",
            "team": "CRO",
            "opponent": "PAN",
            "line": "1+ Shots on Goal",
            "score": 64.82,
            "confidence": 65,
            "tier": "B",
            "reason": "SOG \u03bb 1.04 | Raw SOG/m 1.00 | Sample 6 | FIFA World Cup | Shrunk to M prior",
            "sim_prob_pct": 64.82,
            "model_hit_rate": 0.6482
          },
          {
            "player_id": "103485",
            "player_name": "Ivan Perisic",
            "team": "CRO",
            "opponent": "PAN",
            "line": "1+ Shots on Goal",
            "score": 59.32,
            "confidence": 59,
            "tier": "B",
            "reason": "SOG \u03bb 0.90 | Raw SOG/m 0.71 | Sample 14 | FIFA World Cup | Shrunk to F prior",
            "sim_prob_pct": 59.32,
            "model_hit_rate": 0.5932
          },
          {
            "player_id": "155913",
            "player_name": "Cecilio Waterman",
            "team": "PAN",
            "opponent": "CRO",
            "line": "1+ Shots on Goal",
            "score": 57.63,
            "confidence": 58,
            "tier": "B",
            "reason": "SOG \u03bb 0.86 | Raw SOG/m 1.27 | Sample 15 | FIFA World Cup | Shrunk to F prior",
            "sim_prob_pct": 57.63,
            "model_hit_rate": 0.5763
          },
          {
            "player_id": "277128",
            "player_name": "Petar Musa",
            "team": "CRO",
            "opponent": "PAN",
            "line": "2+ Shots on Goal",
            "score": 56.73,
            "confidence": 57,
            "tier": "B",
            "reason": "SOG \u03bb 1.90 | Raw SOG/m 1.64 | Sample 14 | FIFA World Cup | Shrunk to F prior",
            "sim_prob_pct": 56.73,
            "model_hit_rate": 0.5673
          },
          {
            "player_id": "340539",
            "player_name": "Azarias Londo\u00f1o",
            "team": "PAN",
            "opponent": "CRO",
            "line": "1+ Shots on Goal",
            "score": 54.28,
            "confidence": 54,
            "tier": "C",
            "reason": "SOG \u03bb 0.78 | Raw SOG/m 1.25 | Sample 4 | FIFA World Cup | Shrunk to F prior",
            "sim_prob_pct": 54.28,
            "model_hit_rate": 0.5428
          },
          {
            "player_id": "76762",
            "player_name": "Luka Modric",
            "team": "CRO",
            "opponent": "PAN",
            "line": "1+ Shots on Goal",
            "score": 53.92,
            "confidence": 54,
            "tier": "C",
            "reason": "SOG \u03bb 0.77 | Raw SOG/m 0.75 | Sample 4 | FIFA World Cup | Shrunk to M prior",
            "sim_prob_pct": 53.92,
            "model_hit_rate": 0.5392
          },
          {
            "player_id": "267996",
            "player_name": "Jos\u00e9 Fajardo",
            "team": "PAN",
            "opponent": "CRO",
            "line": "1+ Shots on Goal",
            "score": 52.38,
            "confidence": 52,
            "tier": "C",
            "reason": "SOG \u03bb 0.74 | Raw SOG/m 1.09 | Sample 11 | FIFA World Cup | Shrunk to F prior",
            "sim_prob_pct": 52.38,
            "model_hit_rate": 0.5238
          },
          {
            "player_id": "324270",
            "player_name": "Marco Pasalic",
            "team": "CRO",
            "opponent": "PAN",
            "line": "1+ Shots on Goal",
            "score": 49.54,
            "confidence": 50,
            "tier": "C",
            "reason": "SOG \u03bb 0.68 | Raw SOG/m 0.50 | Sample 10 | FIFA World Cup | Shrunk to F prior",
            "sim_prob_pct": 49.54,
            "model_hit_rate": 0.4954
          }
        ],
        "BTTS": [
          {
            "player_id": "760460-btts",
            "player_name": "Both Teams to Score",
            "team": "PAN",
            "opponent": "CRO",
            "line": "BTTS Yes",
            "score": 57.57,
            "confidence": 58,
            "tier": "B",
            "reason": "Home score 66.1% | Away score 87.1% | xG 1.08-2.05",
            "sim_prob_pct": 57.57,
            "model_hit_rate": 0.5757
          }
        ],
        "1H": [
          {
            "player_id": "760460-1h",
            "player_name": "First Half Goal",
            "team": "PAN",
            "opponent": "CRO",
            "line": "1H Over 0.5 Goals",
            "score": 76.31,
            "confidence": 76,
            "tier": "A",
            "reason": "First-half \u03bb 1.44 | 46% goal-time share | Full-match xG 3.13",
            "sim_prob_pct": 76.31,
            "model_hit_rate": 0.7631
          }
        ],
        "1HML": [
          {
            "player_id": "760460-1hml",
            "player_name": "CRO",
            "team": "CRO",
            "opponent": "PAN",
            "line": "1H Moneyline",
            "score": 45.03,
            "confidence": 45,
            "tier": "C",
            "reason": "1H Poisson 45.0% | 1H xG 0.50-0.94",
            "sim_prob_pct": 45.03,
            "model_hit_rate": 0.4503
          }
        ],
        "OU": [
          {
            "player_id": "760460-ou",
            "player_name": "Match Total",
            "team": "PAN",
            "opponent": "CRO",
            "line": "Over 2.5 Goals",
            "score": 59.55,
            "confidence": 60,
            "tier": "B",
            "reason": "Total \u03bb 3.13 | Model over 60.6% | Calibrated over 59.5%",
            "sim_prob_pct": 59.55,
            "model_hit_rate": 0.5955,
            "implied_odds": "-155"
          }
        ],
        "ML": [
          {
            "player_id": "760460-ml",
            "player_name": "CRO",
            "team": "CRO",
            "opponent": "PAN",
            "line": "Moneyline",
            "score": 61.99,
            "confidence": 62,
            "tier": "B",
            "reason": "Calibrated 62.0% | Poisson 59.7% | Market 65.2%",
            "sim_prob_pct": 61.99,
            "model_hit_rate": 0.6199,
            "implied_odds": "-215"
          }
        ]
      }
    },
    {
      "game_id": "760459",
      "matchup": "COD @ COL",
      "time": "FIFA World Cup | Scheduled",
      "top_signals": [
        {
          "market": "SOT",
          "player_name": "James Rodr\u00edguez",
          "line": "1+ Shots on Goal",
          "score": 68.32,
          "confidence": 68,
          "tier": "B",
          "player_id": "82816"
        },
        {
          "market": "SHOTS",
          "player_name": "Cucho Hern\u00e1ndez",
          "line": "2+ Shots",
          "score": 94.33,
          "confidence": 94,
          "tier": "A",
          "player_id": "336809"
        },
        {
          "market": "BTTS",
          "player_name": "Both Teams to Score",
          "line": "BTTS No",
          "score": 50.06,
          "confidence": 50,
          "tier": "C",
          "player_id": "760459-btts"
        }
      ],
      "markets": {
        "GS": [
          {
            "player_id": "272722",
            "player_name": "Luis Su\u00e1rez",
            "team": "COL",
            "opponent": "COD",
            "line": "Anytime Goal",
            "score": 57.65,
            "confidence": 58,
            "tier": "B",
            "reason": "Goal \u03bb 0.86 | Raw G/m 0.76 | Team xG 1.85 | Sample 49 | FIFA World Cup | Shrunk to F prior",
            "sim_prob_pct": 57.65,
            "model_hit_rate": 0.5765
          },
          {
            "player_id": "257390",
            "player_name": "Luis D\u00edaz",
            "team": "COL",
            "opponent": "COD",
            "line": "Anytime Goal",
            "score": 46.78,
            "confidence": 47,
            "tier": "C",
            "reason": "Goal \u03bb 0.63 | Raw G/m 0.55 | Team xG 1.85 | Sample 51 | FIFA World Cup | Shrunk to F prior",
            "sim_prob_pct": 46.78,
            "model_hit_rate": 0.4678
          },
          {
            "player_id": "336809",
            "player_name": "Cucho Hern\u00e1ndez",
            "team": "COL",
            "opponent": "COD",
            "line": "Anytime Goal",
            "score": 43.53,
            "confidence": 44,
            "tier": "C",
            "reason": "Goal \u03bb 0.57 | Raw G/m 0.57 | Team xG 1.85 | Sample 7 | FIFA World Cup | Shrunk to F prior",
            "sim_prob_pct": 43.53,
            "model_hit_rate": 0.4353
          },
          {
            "player_id": "239566",
            "player_name": "Jhon Arias",
            "team": "COL",
            "opponent": "COD",
            "line": "Anytime Goal",
            "score": 36.27,
            "confidence": 36,
            "tier": "C",
            "reason": "Goal \u03bb 0.45 | Raw G/m 0.42 | Team xG 1.85 | Sample 24 | FIFA World Cup | Shrunk to M prior",
            "sim_prob_pct": 36.27,
            "model_hit_rate": 0.3627
          },
          {
            "player_id": "130545",
            "player_name": "Ga\u00ebl Kakuta",
            "team": "COD",
            "opponent": "COL",
            "line": "Anytime Goal",
            "score": 26.4,
            "confidence": 26,
            "tier": "C",
            "reason": "Goal \u03bb 0.31 | Raw G/m 1.00 | Team xG 0.90 | Sample 2 | FIFA World Cup | Shrunk to M prior",
            "sim_prob_pct": 26.4,
            "model_hit_rate": 0.264
          },
          {
            "player_id": "255295",
            "player_name": "J\u00e1minton Campaz",
            "team": "COL",
            "opponent": "COD",
            "line": "Anytime Goal",
            "score": 21.62,
            "confidence": 22,
            "tier": "C",
            "reason": "Goal \u03bb 0.24 | Raw G/m 0.23 | Team xG 1.85 | Sample 13 | FIFA World Cup | Shrunk to M prior",
            "sim_prob_pct": 21.62,
            "model_hit_rate": 0.2162
          },
          {
            "player_id": "301520",
            "player_name": "Richard R\u00edos",
            "team": "COL",
            "opponent": "COD",
            "line": "Anytime Goal",
            "score": 21.26,
            "confidence": 21,
            "tier": "C",
            "reason": "Goal \u03bb 0.24 | Raw G/m 0.21 | Team xG 1.85 | Sample 38 | FIFA World Cup | Shrunk to M prior",
            "sim_prob_pct": 21.26,
            "model_hit_rate": 0.2126
          },
          {
            "player_id": "224077",
            "player_name": "Yoane Wissa",
            "team": "COD",
            "opponent": "COL",
            "line": "Anytime Goal",
            "score": 21.07,
            "confidence": 21,
            "tier": "C",
            "reason": "Goal \u03bb 0.24 | Raw G/m 0.40 | Team xG 0.90 | Sample 5 | FIFA World Cup | Shrunk to F prior",
            "sim_prob_pct": 21.07,
            "model_hit_rate": 0.2107
          },
          {
            "player_id": "177780",
            "player_name": "Juan Fernando Quintero",
            "team": "COL",
            "opponent": "COD",
            "line": "Anytime Goal",
            "score": 20.25,
            "confidence": 20,
            "tier": "C",
            "reason": "Goal \u03bb 0.23 | Raw G/m 0.22 | Team xG 1.85 | Sample 9 | FIFA World Cup | Shrunk to M prior",
            "sim_prob_pct": 20.25,
            "model_hit_rate": 0.2025
          },
          {
            "player_id": "330924",
            "player_name": "Andr\u00e9s G\u00f3mez",
            "team": "COL",
            "opponent": "COD",
            "line": "Anytime Goal",
            "score": 19.73,
            "confidence": 20,
            "tier": "C",
            "reason": "Goal \u03bb 0.22 | Raw G/m 0.17 | Team xG 1.85 | Sample 23 | FIFA World Cup | Shrunk to F prior",
            "sim_prob_pct": 19.73,
            "model_hit_rate": 0.1973
          }
        ],
        "AST": [
          {
            "player_id": "82816",
            "player_name": "James Rodr\u00edguez",
            "team": "COL",
            "opponent": "COD",
            "line": "Assist",
            "score": 41.08,
            "confidence": 41,
            "tier": "C",
            "reason": "Assist \u03bb 0.53 | Raw A/m 0.57 | Team xG 1.85 | Sample 7 | FIFA World Cup | Shrunk to M prior",
            "sim_prob_pct": 41.08,
            "model_hit_rate": 0.4108
          },
          {
            "player_id": "257390",
            "player_name": "Luis D\u00edaz",
            "team": "COL",
            "opponent": "COD",
            "line": "Assist",
            "score": 37.4,
            "confidence": 37,
            "tier": "C",
            "reason": "Assist \u03bb 0.47 | Raw A/m 0.41 | Team xG 1.85 | Sample 51 | FIFA World Cup | Shrunk to F prior",
            "sim_prob_pct": 37.4,
            "model_hit_rate": 0.374
          },
          {
            "player_id": "255295",
            "player_name": "J\u00e1minton Campaz",
            "team": "COL",
            "opponent": "COD",
            "line": "Assist",
            "score": 33.26,
            "confidence": 33,
            "tier": "C",
            "reason": "Assist \u03bb 0.40 | Raw A/m 0.38 | Team xG 1.85 | Sample 13 | FIFA World Cup | Shrunk to M prior",
            "sim_prob_pct": 33.26,
            "model_hit_rate": 0.3326
          },
          {
            "player_id": "177780",
            "player_name": "Juan Fernando Quintero",
            "team": "COL",
            "opponent": "COD",
            "line": "Assist",
            "score": 29.0,
            "confidence": 29,
            "tier": "C",
            "reason": "Assist \u03bb 0.34 | Raw A/m 0.33 | Team xG 1.85 | Sample 9 | FIFA World Cup | Shrunk to M prior",
            "sim_prob_pct": 29.0,
            "model_hit_rate": 0.29
          },
          {
            "player_id": "164756",
            "player_name": "Santiago Arias",
            "team": "COL",
            "opponent": "COD",
            "line": "Assist",
            "score": 26.71,
            "confidence": 27,
            "tier": "C",
            "reason": "Assist \u03bb 0.31 | Raw A/m 0.31 | Team xG 1.85 | Sample 13 | FIFA World Cup | Shrunk to D prior",
            "sim_prob_pct": 26.71,
            "model_hit_rate": 0.2671
          },
          {
            "player_id": "352285",
            "player_name": "Brian Cipenga",
            "team": "COD",
            "opponent": "COL",
            "line": "Assist",
            "score": 22.68,
            "confidence": 23,
            "tier": "C",
            "reason": "Assist \u03bb 0.26 | Raw A/m 0.42 | Team xG 0.90 | Sample 24 | FIFA World Cup | Shrunk to F prior",
            "sim_prob_pct": 22.68,
            "model_hit_rate": 0.2268
          },
          {
            "player_id": "165892",
            "player_name": "Arthur Masuaku",
            "team": "COD",
            "opponent": "COL",
            "line": "Assist",
            "score": 18.97,
            "confidence": 19,
            "tier": "C",
            "reason": "Assist \u03bb 0.21 | Raw A/m 0.50 | Team xG 0.90 | Sample 4 | FIFA World Cup | Shrunk to D prior",
            "sim_prob_pct": 18.97,
            "model_hit_rate": 0.1897
          },
          {
            "player_id": "130545",
            "player_name": "Ga\u00ebl Kakuta",
            "team": "COD",
            "opponent": "COL",
            "line": "Assist",
            "score": 17.9,
            "confidence": 18,
            "tier": "C",
            "reason": "Assist \u03bb 0.20 | Raw A/m 0.50 | Team xG 0.90 | Sample 2 | FIFA World Cup | Shrunk to M prior",
            "sim_prob_pct": 17.9,
            "model_hit_rate": 0.179
          },
          {
            "player_id": "208700",
            "player_name": "Jorge Carrascal",
            "team": "COL",
            "opponent": "COD",
            "line": "Assist",
            "score": 17.77,
            "confidence": 18,
            "tier": "C",
            "reason": "Assist \u03bb 0.20 | Raw A/m 0.17 | Team xG 1.85 | Sample 18 | FIFA World Cup | Shrunk to M prior",
            "sim_prob_pct": 17.77,
            "model_hit_rate": 0.1777
          },
          {
            "player_id": "272722",
            "player_name": "Luis Su\u00e1rez",
            "team": "COL",
            "opponent": "COD",
            "line": "Assist",
            "score": 17.4,
            "confidence": 17,
            "tier": "C",
            "reason": "Assist \u03bb 0.19 | Raw A/m 0.16 | Team xG 1.85 | Sample 49 | FIFA World Cup | Shrunk to F prior",
            "sim_prob_pct": 17.4,
            "model_hit_rate": 0.174
          }
        ],
        "SHOTS": [
          {
            "player_id": "336809",
            "player_name": "Cucho Hern\u00e1ndez",
            "team": "COL",
            "opponent": "COD",
            "line": "2+ Shots",
            "score": 94.33,
            "confidence": 94,
            "tier": "A",
            "reason": "Shots \u03bb 4.59 | Raw shots/m 4.43 | Sample 7 | FIFA World Cup | Shrunk to F prior",
            "sim_prob_pct": 94.33,
            "model_hit_rate": 0.9433
          },
          {
            "player_id": "272722",
            "player_name": "Luis Su\u00e1rez",
            "team": "COL",
            "opponent": "COD",
            "line": "2+ Shots",
            "score": 93.11,
            "confidence": 93,
            "tier": "A",
            "reason": "Shots \u03bb 4.35 | Raw shots/m 3.76 | Sample 49 | FIFA World Cup | Shrunk to F prior",
            "sim_prob_pct": 93.11,
            "model_hit_rate": 0.9311
          },
          {
            "player_id": "177780",
            "player_name": "Juan Fernando Quintero",
            "team": "COL",
            "opponent": "COD",
            "line": "2+ Shots",
            "score": 92.45,
            "confidence": 92,
            "tier": "A",
            "reason": "Shots \u03bb 4.24 | Raw shots/m 4.11 | Sample 9 | FIFA World Cup | Shrunk to M prior",
            "sim_prob_pct": 92.45,
            "model_hit_rate": 0.9245
          },
          {
            "player_id": "255295",
            "player_name": "J\u00e1minton Campaz",
            "team": "COL",
            "opponent": "COD",
            "line": "2+ Shots",
            "score": 90.66,
            "confidence": 91,
            "tier": "A",
            "reason": "Shots \u03bb 3.98 | Raw shots/m 3.69 | Sample 13 | FIFA World Cup | Shrunk to M prior",
            "sim_prob_pct": 90.66,
            "model_hit_rate": 0.9066
          },
          {
            "player_id": "330924",
            "player_name": "Andr\u00e9s G\u00f3mez",
            "team": "COL",
            "opponent": "COD",
            "line": "2+ Shots",
            "score": 89.87,
            "confidence": 90,
            "tier": "A",
            "reason": "Shots \u03bb 3.87 | Raw shots/m 3.39 | Sample 23 | FIFA World Cup | Shrunk to F prior",
            "sim_prob_pct": 89.87,
            "model_hit_rate": 0.8987
          },
          {
            "player_id": "257390",
            "player_name": "Luis D\u00edaz",
            "team": "COL",
            "opponent": "COD",
            "line": "2+ Shots",
            "score": 85.41,
            "confidence": 85,
            "tier": "A",
            "reason": "Shots \u03bb 3.41 | Raw shots/m 2.92 | Sample 51 | FIFA World Cup | Shrunk to F prior",
            "sim_prob_pct": 85.41,
            "model_hit_rate": 0.8541
          },
          {
            "player_id": "82816",
            "player_name": "James Rodr\u00edguez",
            "team": "COL",
            "opponent": "COD",
            "line": "2+ Shots",
            "score": 79.36,
            "confidence": 79,
            "tier": "A",
            "reason": "Shots \u03bb 2.95 | Raw shots/m 2.86 | Sample 7 | FIFA World Cup | Shrunk to M prior",
            "sim_prob_pct": 79.36,
            "model_hit_rate": 0.7936
          },
          {
            "player_id": "239566",
            "player_name": "Jhon Arias",
            "team": "COL",
            "opponent": "COD",
            "line": "2+ Shots",
            "score": 74.34,
            "confidence": 74,
            "tier": "A",
            "reason": "Shots \u03bb 2.66 | Raw shots/m 2.33 | Sample 24 | FIFA World Cup | Shrunk to M prior",
            "sim_prob_pct": 74.34,
            "model_hit_rate": 0.7434
          },
          {
            "player_id": "341736",
            "player_name": "Gustavo Puerta",
            "team": "COL",
            "opponent": "COD",
            "line": "1+ Shots",
            "score": 73.62,
            "confidence": 74,
            "tier": "A",
            "reason": "Shots \u03bb 1.33 | Raw shots/m 1.12 | Sample 33 | FIFA World Cup | Shrunk to M prior",
            "sim_prob_pct": 73.62,
            "model_hit_rate": 0.7362
          },
          {
            "player_id": "196901",
            "player_name": "Yerry Mina",
            "team": "COL",
            "opponent": "COD",
            "line": "1+ Shots",
            "score": 70.48,
            "confidence": 70,
            "tier": "B",
            "reason": "Shots \u03bb 1.22 | Raw shots/m 2.00 | Sample 1 | FIFA World Cup | Shrunk to D prior",
            "sim_prob_pct": 70.48,
            "model_hit_rate": 0.7048
          }
        ],
        "SOT": [
          {
            "player_id": "82816",
            "player_name": "James Rodr\u00edguez",
            "team": "COL",
            "opponent": "COD",
            "line": "1+ Shots on Goal",
            "score": 68.32,
            "confidence": 68,
            "tier": "B",
            "reason": "SOG \u03bb 1.15 | Raw SOG/m 1.14 | Sample 7 | FIFA World Cup | Shrunk to M prior",
            "sim_prob_pct": 68.32,
            "model_hit_rate": 0.6832
          },
          {
            "player_id": "330924",
            "player_name": "Andr\u00e9s G\u00f3mez",
            "team": "COL",
            "opponent": "COD",
            "line": "1+ Shots on Goal",
            "score": 67.26,
            "confidence": 67,
            "tier": "B",
            "reason": "SOG \u03bb 1.12 | Raw SOG/m 0.96 | Sample 23 | FIFA World Cup | Shrunk to F prior",
            "sim_prob_pct": 67.26,
            "model_hit_rate": 0.6726
          },
          {
            "player_id": "176058",
            "player_name": "Jhon C\u00f3rdoba",
            "team": "COL",
            "opponent": "COD",
            "line": "1+ Shots on Goal",
            "score": 65.57,
            "confidence": 66,
            "tier": "B",
            "reason": "SOG \u03bb 1.07 | Raw SOG/m 0.92 | Sample 12 | FIFA World Cup | Shrunk to F prior",
            "sim_prob_pct": 65.57,
            "model_hit_rate": 0.6557
          },
          {
            "player_id": "177780",
            "player_name": "Juan Fernando Quintero",
            "team": "COL",
            "opponent": "COD",
            "line": "2+ Shots on Goal",
            "score": 62.58,
            "confidence": 63,
            "tier": "B",
            "reason": "SOG \u03bb 2.12 | Raw SOG/m 2.11 | Sample 9 | FIFA World Cup | Shrunk to M prior",
            "sim_prob_pct": 62.58,
            "model_hit_rate": 0.6258
          },
          {
            "player_id": "208700",
            "player_name": "Jorge Carrascal",
            "team": "COL",
            "opponent": "COD",
            "line": "1+ Shots on Goal",
            "score": 58.17,
            "confidence": 58,
            "tier": "B",
            "reason": "SOG \u03bb 0.87 | Raw SOG/m 0.78 | Sample 18 | FIFA World Cup | Shrunk to M prior",
            "sim_prob_pct": 58.17,
            "model_hit_rate": 0.5817
          },
          {
            "player_id": "255295",
            "player_name": "J\u00e1minton Campaz",
            "team": "COL",
            "opponent": "COD",
            "line": "2+ Shots on Goal",
            "score": 58.01,
            "confidence": 58,
            "tier": "B",
            "reason": "SOG \u03bb 1.95 | Raw SOG/m 1.85 | Sample 13 | FIFA World Cup | Shrunk to M prior",
            "sim_prob_pct": 58.01,
            "model_hit_rate": 0.5801
          },
          {
            "player_id": "336809",
            "player_name": "Cucho Hern\u00e1ndez",
            "team": "COL",
            "opponent": "COD",
            "line": "2+ Shots on Goal",
            "score": 57.21,
            "confidence": 57,
            "tier": "B",
            "reason": "SOG \u03bb 1.92 | Raw SOG/m 1.86 | Sample 7 | FIFA World Cup | Shrunk to F prior",
            "sim_prob_pct": 57.21,
            "model_hit_rate": 0.5721
          },
          {
            "player_id": "272722",
            "player_name": "Luis Su\u00e1rez",
            "team": "COL",
            "opponent": "COD",
            "line": "2+ Shots on Goal",
            "score": 57.0,
            "confidence": 57,
            "tier": "B",
            "reason": "SOG \u03bb 1.91 | Raw SOG/m 1.65 | Sample 49 | FIFA World Cup | Shrunk to F prior",
            "sim_prob_pct": 57.0,
            "model_hit_rate": 0.57
          },
          {
            "player_id": "301520",
            "player_name": "Richard R\u00edos",
            "team": "COL",
            "opponent": "COD",
            "line": "1+ Shots on Goal",
            "score": 50.41,
            "confidence": 50,
            "tier": "C",
            "reason": "SOG \u03bb 0.70 | Raw SOG/m 0.61 | Sample 38 | FIFA World Cup | Shrunk to M prior",
            "sim_prob_pct": 50.41,
            "model_hit_rate": 0.5041
          },
          {
            "player_id": "257390",
            "player_name": "Luis D\u00edaz",
            "team": "COL",
            "opponent": "COD",
            "line": "2+ Shots on Goal",
            "score": 48.1,
            "confidence": 48,
            "tier": "C",
            "reason": "SOG \u03bb 1.62 | Raw SOG/m 1.39 | Sample 51 | FIFA World Cup | Shrunk to F prior",
            "sim_prob_pct": 48.1,
            "model_hit_rate": 0.481
          }
        ],
        "BTTS": [
          {
            "player_id": "760459-btts",
            "player_name": "Both Teams to Score",
            "team": "COL",
            "opponent": "COD",
            "line": "BTTS No",
            "score": 50.06,
            "confidence": 50,
            "tier": "C",
            "reason": "Home score 84.2% | Away score 59.3% | xG 1.85-0.90",
            "sim_prob_pct": 50.06,
            "model_hit_rate": 0.5006
          }
        ],
        "1H": [
          {
            "player_id": "760459-1h",
            "player_name": "First Half Goal",
            "team": "COL",
            "opponent": "COD",
            "line": "1H Over 0.5 Goals",
            "score": 71.7,
            "confidence": 72,
            "tier": "B",
            "reason": "First-half \u03bb 1.26 | 46% goal-time share | Full-match xG 2.74",
            "sim_prob_pct": 71.7,
            "model_hit_rate": 0.717
          }
        ],
        "1HML": [
          {
            "player_id": "760459-1hml",
            "player_name": "COL",
            "team": "COL",
            "opponent": "COD",
            "line": "1H Moneyline",
            "score": 43.85,
            "confidence": 44,
            "tier": "C",
            "reason": "1H Poisson 43.9% | 1H xG 0.85-0.41",
            "sim_prob_pct": 43.85,
            "model_hit_rate": 0.4385
          }
        ],
        "OU": [
          {
            "player_id": "760459-ou",
            "player_name": "Match Total",
            "team": "COL",
            "opponent": "COD",
            "line": "Under 2.5 Goals",
            "score": 50.72,
            "confidence": 51,
            "tier": "C",
            "reason": "Total \u03bb 2.74 | Model over 51.7% | Calibrated under 50.7%",
            "sim_prob_pct": 50.72,
            "model_hit_rate": 0.5072,
            "implied_odds": "-140"
          }
        ],
        "ML": [
          {
            "player_id": "760459-ml",
            "player_name": "COL",
            "team": "COL",
            "opponent": "COD",
            "line": "Moneyline",
            "score": 60.66,
            "confidence": 61,
            "tier": "B",
            "reason": "Calibrated 60.7% | Poisson 59.6% | Market 62.1%",
            "sim_prob_pct": 60.66,
            "model_hit_rate": 0.6066,
            "implied_odds": "-180"
          }
        ]
      }
    }
  ]
}