{
  "sport": "TENNIS",
  "date": "2026-05-13",
  "last_updated": "6:14 PM ET",
  "pinned_board": {
    "title": "Match Win Top 10",
    "market": "ML",
    "players": [
      {
        "player_id": "7833",
        "player_name": "Luciano Darderi",
        "team": "ATP",
        "opponent": "Rafael Jodar",
        "line": "Match Winner",
        "score": 69.15,
        "confidence": 69,
        "tier": "B",
        "reason": "Rank 20 vs 34 | Form 3-0 vs 3-0 | Luciano Darderi vs Rafael Jodar"
      },
      {
        "player_id": "7833",
        "player_name": "Luciano Darderi",
        "team": "WTA",
        "opponent": "Rafael Jodar",
        "line": "Match Winner",
        "score": 69.15,
        "confidence": 69,
        "tier": "B",
        "reason": "Rank 18 vs 32 | Form 3-0 vs 3-0 | Luciano Darderi vs Rafael Jodar"
      }
    ]
  },
  "games": [
    {
      "game_id": "175362",
      "matchup": "Luciano Darderi vs Rafael Jodar",
      "time": "ATP | Internazionali BNL d'Italia | 1st",
      "top_signals": [
        {
          "market": "ML",
          "player_name": "Luciano Darderi",
          "line": "Match Winner",
          "score": 69.15,
          "confidence": 69,
          "tier": "B",
          "player_id": "7833"
        },
        {
          "market": "Sets",
          "player_name": "Luciano Darderi",
          "line": "Over 3.5 Sets",
          "score": 64.0,
          "confidence": 64,
          "tier": "B",
          "player_id": "175362-sets"
        },
        {
          "market": "O/U",
          "player_name": "Match Total",
          "line": "Over 36.5 Games",
          "score": 71.0,
          "confidence": 71,
          "tier": "B",
          "player_id": "175362-ou"
        }
      ],
      "markets": {
        "ML": [
          {
            "player_id": "7833",
            "player_name": "Luciano Darderi",
            "team": "ATP",
            "opponent": "Rafael Jodar",
            "line": "Match Winner",
            "score": 69.15,
            "confidence": 69,
            "tier": "B",
            "reason": "Rank 20 vs 34 | Form 3-0 vs 3-0 | Luciano Darderi vs Rafael Jodar"
          }
        ],
        "O/U": [
          {
            "player_id": "175362-ou",
            "player_name": "Match Total",
            "team": "ATP",
            "opponent": "Luciano Darderi vs Rafael Jodar",
            "line": "Over 36.5 Games",
            "score": 71.0,
            "confidence": 71,
            "tier": "B",
            "reason": "Round Quarterfinal | Rank gap 14 | Form gap -0.06"
          }
        ],
        "Sets": [
          {
            "player_id": "175362-sets",
            "player_name": "Luciano Darderi",
            "team": "ATP",
            "opponent": "Rafael Jodar",
            "line": "Over 3.5 Sets",
            "score": 64.0,
            "confidence": 64,
            "tier": "B",
            "reason": "Best-of-5 | Sets 6-2 | Rank gap 14"
          }
        ]
      }
    },
    {
      "game_id": "175362",
      "matchup": "Luciano Darderi vs Rafael Jodar",
      "time": "WTA | Internazionali BNL d'Italia | 1st",
      "top_signals": [
        {
          "market": "ML",
          "player_name": "Luciano Darderi",
          "line": "Match Winner",
          "score": 69.15,
          "confidence": 69,
          "tier": "B",
          "player_id": "7833"
        },
        {
          "market": "Sets",
          "player_name": "Luciano Darderi",
          "line": "Over 2.5 Sets",
          "score": 63.0,
          "confidence": 63,
          "tier": "B",
          "player_id": "175362-sets"
        },
        {
          "market": "O/U",
          "player_name": "Match Total",
          "line": "Over 22.5 Games",
          "score": 72.0,
          "confidence": 72,
          "tier": "B",
          "player_id": "175362-ou"
        }
      ],
      "markets": {
        "ML": [
          {
            "player_id": "7833",
            "player_name": "Luciano Darderi",
            "team": "WTA",
            "opponent": "Rafael Jodar",
            "line": "Match Winner",
            "score": 69.15,
            "confidence": 69,
            "tier": "B",
            "reason": "Rank 18 vs 32 | Form 3-0 vs 3-0 | Luciano Darderi vs Rafael Jodar"
          }
        ],
        "O/U": [
          {
            "player_id": "175362-ou",
            "player_name": "Match Total",
            "team": "WTA",
            "opponent": "Luciano Darderi vs Rafael Jodar",
            "line": "Over 22.5 Games",
            "score": 72.0,
            "confidence": 72,
            "tier": "B",
            "reason": "Round Quarterfinal | Rank gap 14 | Form gap -0.06"
          }
        ],
        "Sets": [
          {
            "player_id": "175362-sets",
            "player_name": "Luciano Darderi",
            "team": "WTA",
            "opponent": "Rafael Jodar",
            "line": "Over 2.5 Sets",
            "score": 63.0,
            "confidence": 63,
            "tier": "B",
            "reason": "Best-of-3 | Sets 6-2 | Rank gap 14"
          }
        ]
      }
    }
  ]
}