{
  "sport": "WNBA",
  "date": "2026-05-08",
  "last_updated": "5:31 AM ET",
  "hero_pick": {
    "player_id": "4281930",
    "player_name": "Anneli Maley",
    "team": "NY",
    "opponent": "CON",
    "market": "PTS",
    "line": "13+ PTS",
    "score": 87.37,
    "confidence": 87,
    "tier": "B",
    "reason": "Sample 2 | L10 100% | L5 100% | USG 28% | MIN 27.0 | PTS matchup 1.05x | Prev 13.0 | Pre 13.0 | Home boost",
    "label": "Pick of the Day"
  },
  "game_clusters": [
    {
      "game_id": "401856890",
      "matchup": "CON @ NY",
      "top_score": 83.94,
      "signals": [
        {
          "player_name": "Anneli Maley",
          "market": "PTS",
          "line": "13+ PTS",
          "score": 87.37,
          "tier": "B"
        },
        {
          "player_name": "Breanna Stewart",
          "market": "AST",
          "line": "2+ AST",
          "score": 83.75,
          "tier": "A"
        },
        {
          "player_name": "Derin Erdogan",
          "market": "3PM",
          "line": "1+ 3PM",
          "score": 80.71,
          "tier": "C"
        }
      ]
    },
    {
      "game_id": "401856891",
      "matchup": "WSH @ TOR",
      "top_score": 81.86,
      "signals": [
        {
          "player_name": "Lauren Betts",
          "market": "REB",
          "line": "4+ REB",
          "score": 86.34,
          "tier": "B"
        },
        {
          "player_name": "Kia Nurse",
          "market": "3PM",
          "line": "1+ 3PM",
          "score": 81.29,
          "tier": "C"
        },
        {
          "player_name": "Kiki Rice",
          "market": "AST",
          "line": "2+ AST",
          "score": 77.94,
          "tier": "C"
        }
      ]
    },
    {
      "game_id": "401856892",
      "matchup": "GS @ SEA",
      "top_score": 78.05,
      "signals": [
        {
          "player_name": "Jaelyn Brown",
          "market": "3PM",
          "line": "1+ 3PM",
          "score": 79.25,
          "tier": "C"
        },
        {
          "player_name": "Flau'jae Johnson",
          "market": "REB",
          "line": "3+ REB",
          "score": 77.72,
          "tier": "C"
        },
        {
          "player_name": "Janelle Salaun",
          "market": "REB",
          "line": "6+ REB",
          "score": 77.19,
          "tier": "B"
        }
      ]
    }
  ],
  "section_boards": {
    "PTS": {
      "title": "Scoring Board",
      "market": "PTS",
      "players": [
        {
          "player_id": "4281930",
          "player_name": "Anneli Maley",
          "team": "NY",
          "opponent": "CON",
          "line": "13+ PTS",
          "score": 87.37,
          "confidence": 87,
          "tier": "B",
          "reason": "Sample 2 | L10 100% | L5 100% | USG 28% | MIN 27.0 | PTS matchup 1.05x | Prev 13.0 | Pre 13.0 | Home boost"
        },
        {
          "player_id": "4398935",
          "player_name": "Veronica Burton",
          "team": "GS",
          "opponent": "SEA",
          "line": "11+ PTS",
          "score": 73.26,
          "confidence": 73,
          "tier": "B",
          "reason": "Sample 12 | L10 70% | L5 80% | USG 45% | MIN 29.7 | PTS matchup 1.03x | Prev 13.0 | Pre 14.0"
        },
        {
          "player_id": "2998928",
          "player_name": "Breanna Stewart",
          "team": "NY",
          "opponent": "CON",
          "line": "14+ PTS",
          "score": 72.77,
          "confidence": 73,
          "tier": "A",
          "reason": "Sample 12 | L10 80% | L5 60% | USG 31% | MIN 25.4 | PTS matchup 1.05x | Prev 18.0 | Pre 10.0 | Home boost | Anti-correlation: same team as Anneli Maley"
        },
        {
          "player_id": "2988756",
          "player_name": "Brittney Sykes",
          "team": "TOR",
          "opponent": "WSH",
          "line": "8+ PTS",
          "score": 70.67,
          "confidence": 71,
          "tier": "B",
          "reason": "Sample 11 | L10 70% | L5 60% | USG 27% | MIN 24.6 | PTS matchup 1.03x | Prev 8.6 | Pre 8.0 | Decline 0.17 | Home boost"
        },
        {
          "player_id": "5345320",
          "player_name": "Pauline Astier",
          "team": "NY",
          "opponent": "CON",
          "line": "12+ PTS",
          "score": 70.02,
          "confidence": 70,
          "tier": "B",
          "reason": "Sample 1 | L10 100% | L5 100% | USG 18% | MIN 22.0 | PTS matchup 1.05x | Prev 12.0 | Pre 12.0 | Home boost | Minutes watch | Anti-correlation: same team as Anneli Maley"
        },
        {
          "player_id": "4790264",
          "player_name": "Janelle Salaun",
          "team": "GS",
          "opponent": "SEA",
          "line": "12+ PTS",
          "score": 69.77,
          "confidence": 70,
          "tier": "B",
          "reason": "Sample 11 | L10 60% | L5 80% | USG 38% | MIN 33.0 | PTS matchup 1.03x | Prev 13.8 | Pre 13.8 | Anti-correlation: same team as Veronica Burton"
        },
        {
          "player_id": "4583144",
          "player_name": "Cotie McMahon",
          "team": "WSH",
          "opponent": "TOR",
          "line": "9+ PTS",
          "score": 69.13,
          "confidence": 69,
          "tier": "B",
          "reason": "Sample 2 | L10 100% | L5 100% | USG 19% | MIN 25.0 | PTS matchup 0.98x | Prev 10.0 | Pre 10.0"
        },
        {
          "player_id": "4898384",
          "player_name": "Kiki Iriafen",
          "team": "WSH",
          "opponent": "TOR",
          "line": "13+ PTS",
          "score": 65.83,
          "confidence": 66,
          "tier": "B",
          "reason": "Sample 11 | L10 60% | L5 60% | USG 30% | MIN 25.4 | PTS matchup 0.98x | Prev 14.7 | Pre 11.0 | Uptick 0.13 | Anti-correlation: same team as Cotie McMahon"
        },
        {
          "player_id": "5220150",
          "player_name": "Dominique Malonga",
          "team": "SEA",
          "opponent": "GS",
          "line": "9+ PTS",
          "score": 63.52,
          "confidence": 64,
          "tier": "C",
          "reason": "Sample 11 | L10 60% | L5 80% | USG 25% | MIN 21.7 | PTS matchup 0.94x | Prev 9.9 | Pre 10.0 | Home boost | Minutes watch"
        },
        {
          "player_id": "4790263",
          "player_name": "Iliana Rupert",
          "team": "GS",
          "opponent": "SEA",
          "line": "8+ PTS",
          "score": 62.36,
          "confidence": 62,
          "tier": "B",
          "reason": "Sample 11 | L10 60% | L5 60% | USG 26% | MIN 25.7 | PTS matchup 1.03x | Prev 9.4 | Pre 9.4 | Decline 0.21 | Anti-correlation: same team as Veronica Burton"
        }
      ]
    },
    "AST": {
      "title": "Playmaker Assists",
      "market": "AST",
      "players": [
        {
          "player_id": "2998928",
          "player_name": "Breanna Stewart",
          "team": "NY",
          "opponent": "CON",
          "line": "2+ AST",
          "score": 83.75,
          "confidence": 84,
          "tier": "A",
          "reason": "Sample 12 | L10 80% | L5 80% | USG 31% | MIN 25.4 | AST matchup 1.09x | Prev 2.4 | Pre 1.0 | Home boost"
        },
        {
          "player_id": "4433514",
          "player_name": "Saniya Rivers",
          "team": "CON",
          "opponent": "NY",
          "line": "2+ AST",
          "score": 79.71,
          "confidence": 80,
          "tier": "B",
          "reason": "Sample 12 | L10 60% | L5 100% | USG 30% | MIN 27.8 | AST matchup 1.01x | Prev 2.4 | Pre 3.5 | Uptick 0.42"
        },
        {
          "player_id": "4565505",
          "player_name": "Kiki Rice",
          "team": "TOR",
          "opponent": "WSH",
          "line": "2+ AST",
          "score": 77.94,
          "confidence": 78,
          "tier": "C",
          "reason": "Sample 2 | L10 100% | L5 100% | USG 20% | MIN 20.0 | AST matchup 1.05x | Prev 2.0 | Pre 2.0 | Home boost | Minutes watch"
        },
        {
          "player_id": "5345320",
          "player_name": "Pauline Astier",
          "team": "NY",
          "opponent": "CON",
          "line": "4+ AST",
          "score": 75.4,
          "confidence": 75,
          "tier": "B",
          "reason": "Sample 1 | L10 100% | L5 100% | USG 18% | MIN 22.0 | AST matchup 1.09x | Prev 4.0 | Pre 4.0 | Home boost | Minutes watch | Anti-correlation: same team as Breanna Stewart"
        },
        {
          "player_id": "2999101",
          "player_name": "Jonquel Jones",
          "team": "NY",
          "opponent": "CON",
          "line": "2+ AST",
          "score": 68.95,
          "confidence": 69,
          "tier": "B",
          "reason": "Sample 11 | L10 70% | L5 60% | USG 19% | MIN 24.9 | AST matchup 1.09x | Prev 3.1 | Pre 1.0 | Decline 0.30 | Home boost | Anti-correlation: same team as Breanna Stewart"
        },
        {
          "player_id": "4398935",
          "player_name": "Veronica Burton",
          "team": "GS",
          "opponent": "SEA",
          "line": "7+ AST",
          "score": 68.73,
          "confidence": 69,
          "tier": "B",
          "reason": "Sample 12 | L10 60% | L5 80% | USG 45% | MIN 29.7 | AST matchup 1.00x | Prev 8.5 | Pre 3.0"
        },
        {
          "player_id": "3906753",
          "player_name": "Natisha Hiedeman",
          "team": "SEA",
          "opponent": "GS",
          "line": "3+ AST",
          "score": 68.37,
          "confidence": 68,
          "tier": "C",
          "reason": "Sample 1 | L10 100% | L5 100% | USG 15% | MIN 14.0 | AST matchup 0.98x | Prev 3.0 | Pre 3.0 | Home boost | Minutes watch"
        },
        {
          "player_id": "2569044",
          "player_name": "Temi Fagbenle",
          "team": "TOR",
          "opponent": "WSH",
          "line": "2+ AST",
          "score": 65.74,
          "confidence": 66,
          "tier": "B",
          "reason": "Sample 12 | L10 60% | L5 60% | USG 20% | MIN 24.4 | AST matchup 1.05x | Prev 1.5 | Pre 2.0 | Home boost | Anti-correlation: same team as Kiki Rice"
        },
        {
          "player_id": "4790263",
          "player_name": "Iliana Rupert",
          "team": "GS",
          "opponent": "SEA",
          "line": "2+ AST",
          "score": 63.97,
          "confidence": 64,
          "tier": "B",
          "reason": "Sample 11 | L10 60% | L5 60% | USG 26% | MIN 25.7 | AST matchup 1.00x | Prev 2.2 | Pre 2.2 | Anti-correlation: same team as Veronica Burton"
        },
        {
          "player_id": "4281930",
          "player_name": "Anneli Maley",
          "team": "NY",
          "opponent": "CON",
          "line": "2+ AST",
          "score": 63.58,
          "confidence": 64,
          "tier": "C",
          "reason": "Sample 2 | L10 50% | L5 50% | USG 28% | MIN 27.0 | AST matchup 1.09x | Prev 2.0 | Pre 2.0 | Home boost | Anti-correlation: same team as Breanna Stewart"
        }
      ]
    },
    "REB": {
      "title": "Glass / Rebounds",
      "market": "REB",
      "players": [
        {
          "player_id": "5105737",
          "player_name": "Lauren Betts",
          "team": "WSH",
          "opponent": "TOR",
          "line": "4+ REB",
          "score": 86.34,
          "confidence": 86,
          "tier": "B",
          "reason": "Sample 2 | L10 100% | L5 100% | USG 25% | MIN 24.5 | REB matchup 1.11x | Prev 4.5 | Pre 4.5"
        },
        {
          "player_id": "2998928",
          "player_name": "Breanna Stewart",
          "team": "NY",
          "opponent": "CON",
          "line": "5+ REB",
          "score": 78.06,
          "confidence": 78,
          "tier": "B",
          "reason": "Sample 12 | L10 90% | L5 80% | USG 31% | MIN 25.4 | REB matchup 0.94x | Prev 6.3 | Pre 5.5 | Home boost"
        },
        {
          "player_id": "4698736",
          "player_name": "Flau'jae Johnson",
          "team": "SEA",
          "opponent": "GS",
          "line": "3+ REB",
          "score": 77.72,
          "confidence": 78,
          "tier": "C",
          "reason": "Sample 2 | L10 100% | L5 100% | USG 35% | MIN 21.0 | REB matchup 0.94x | Prev 3.5 | Pre 3.5 | Home boost | Minutes watch"
        },
        {
          "player_id": "4790264",
          "player_name": "Janelle Salaun",
          "team": "GS",
          "opponent": "SEA",
          "line": "6+ REB",
          "score": 77.19,
          "confidence": 77,
          "tier": "B",
          "reason": "Sample 11 | L10 70% | L5 80% | USG 38% | MIN 33.0 | REB matchup 1.03x | Prev 5.9 | Pre 5.9 | Uptick 0.18"
        },
        {
          "player_id": "4433411",
          "player_name": "Angela Dugalic",
          "team": "WSH",
          "opponent": "TOR",
          "line": "5+ REB",
          "score": 76.08,
          "confidence": 76,
          "tier": "C",
          "reason": "Sample 2 | L10 100% | L5 100% | USG 16% | MIN 20.0 | REB matchup 1.11x | Prev 5.5 | Pre 5.5 | Minutes watch | Anti-correlation: same team as Lauren Betts"
        },
        {
          "player_id": "5122345",
          "player_name": "Cassandre Prosper",
          "team": "WSH",
          "opponent": "TOR",
          "line": "3+ REB",
          "score": 74.94,
          "confidence": 75,
          "tier": "C",
          "reason": "Sample 2 | L10 100% | L5 100% | USG 15% | MIN 19.5 | REB matchup 1.11x | Prev 4.0 | Pre 4.0 | Minutes watch | Anti-correlation: same team as Lauren Betts"
        },
        {
          "player_id": "2490553",
          "player_name": "Brittney Griner",
          "team": "CON",
          "opponent": "NY",
          "line": "4+ REB",
          "score": 73.84,
          "confidence": 74,
          "tier": "C",
          "reason": "Sample 2 | L10 100% | L5 100% | USG 23% | MIN 18.5 | REB matchup 0.94x | Prev 4.5 | Pre 4.5 | Minutes watch"
        },
        {
          "player_id": "4398935",
          "player_name": "Veronica Burton",
          "team": "GS",
          "opponent": "SEA",
          "line": "3+ REB",
          "score": 69.6,
          "confidence": 70,
          "tier": "B",
          "reason": "Sample 12 | L10 80% | L5 60% | USG 45% | MIN 29.7 | REB matchup 1.03x | Prev 5.1 | Pre 1.0 | Decline 0.16 | Anti-correlation: same team as Janelle Salaun"
        },
        {
          "player_id": "4001679",
          "player_name": "Julie Allemand",
          "team": "TOR",
          "opponent": "WSH",
          "line": "6+ REB",
          "score": 68.03,
          "confidence": 68,
          "tier": "B",
          "reason": "Sample 1 | L10 100% | L5 100% | USG 7% | MIN 22.0 | REB matchup 1.04x | Prev 6.0 | Pre 6.0 | Home boost | Minutes watch"
        },
        {
          "player_id": "2988756",
          "player_name": "Brittney Sykes",
          "team": "TOR",
          "opponent": "WSH",
          "line": "3+ REB",
          "score": 64.92,
          "confidence": 65,
          "tier": "B",
          "reason": "Sample 11 | L10 60% | L5 40% | USG 27% | MIN 24.6 | REB matchup 1.04x | Prev 2.8 | Pre 1.0 | Home boost | Anti-correlation: same team as Julie Allemand"
        }
      ]
    },
    "3PM": {
      "title": "3PT Heat",
      "market": "3PM",
      "players": [
        {
          "player_id": "3142327",
          "player_name": "Kia Nurse",
          "team": "TOR",
          "opponent": "WSH",
          "line": "1+ 3PM",
          "score": 81.29,
          "confidence": 81,
          "tier": "C",
          "reason": "Sample 2 | L10 100% | L5 100% | USG 22% | MIN 16.5 | 3PM matchup 1.09x | Prev 1.5 | Pre 1.5 | Home boost | Minutes watch"
        },
        {
          "player_id": "4703579",
          "player_name": "Derin Erdogan",
          "team": "NY",
          "opponent": "CON",
          "line": "1+ 3PM",
          "score": 80.71,
          "confidence": 81,
          "tier": "C",
          "reason": "Sample 2 | L10 100% | L5 100% | USG 20% | MIN 16.0 | 3PM matchup 1.20x | Prev 1.0 | Pre 1.0 | Home boost | Minutes watch"
        },
        {
          "player_id": "4066527",
          "player_name": "Jaelyn Brown",
          "team": "SEA",
          "opponent": "GS",
          "line": "1+ 3PM",
          "score": 79.25,
          "confidence": 79,
          "tier": "C",
          "reason": "Sample 2 | L10 100% | L5 100% | USG 18% | MIN 12.0 | 3PM matchup 1.13x | Prev 1.0 | Pre 1.0 | Home boost | Minutes watch"
        },
        {
          "player_id": "2998928",
          "player_name": "Breanna Stewart",
          "team": "NY",
          "opponent": "CON",
          "line": "1+ 3PM",
          "score": 79.05,
          "confidence": 79,
          "tier": "A",
          "reason": "Sample 12 | L10 80% | L5 60% | USG 31% | MIN 25.4 | 3PM matchup 1.20x | Prev 1.0 | Pre 1.0 | Home boost | Anti-correlation: same team as Derin Erdogan"
        },
        {
          "player_id": "4790264",
          "player_name": "Janelle Salaun",
          "team": "GS",
          "opponent": "SEA",
          "line": "2+ 3PM",
          "score": 77.05,
          "confidence": 77,
          "tier": "B",
          "reason": "Sample 11 | L10 80% | L5 80% | USG 38% | MIN 33.0 | 3PM matchup 1.03x | Prev 2.5 | Pre 2.5"
        },
        {
          "player_id": "4790263",
          "player_name": "Iliana Rupert",
          "team": "GS",
          "opponent": "SEA",
          "line": "2+ 3PM",
          "score": 73.17,
          "confidence": 73,
          "tier": "B",
          "reason": "Sample 11 | L10 70% | L5 80% | USG 26% | MIN 25.7 | 3PM matchup 1.03x | Prev 2.3 | Pre 2.3 | Decline 0.21 | Anti-correlation: same team as Janelle Salaun"
        },
        {
          "player_id": "2529622",
          "player_name": "Kayla Thornton",
          "team": "GS",
          "opponent": "SEA",
          "line": "1+ 3PM",
          "score": 72.06,
          "confidence": 72,
          "tier": "C",
          "reason": "Sample 1 | L10 100% | L5 100% | USG 23% | MIN 15.0 | 3PM matchup 1.03x | Prev 1.0 | Pre 1.0 | Minutes watch | Anti-correlation: same team as Janelle Salaun"
        },
        {
          "player_id": "4597509",
          "player_name": "Aaliyah Nye",
          "team": "TOR",
          "opponent": "WSH",
          "line": "1+ 3PM",
          "score": 72.05,
          "confidence": 72,
          "tier": "C",
          "reason": "Sample 2 | L10 100% | L5 100% | USG 13% | MIN 18.5 | 3PM matchup 1.09x | Prev 1.5 | Pre 1.5 | Home boost | Minutes watch | Anti-correlation: same team as Kia Nurse"
        },
        {
          "player_id": "4433514",
          "player_name": "Saniya Rivers",
          "team": "CON",
          "opponent": "NY",
          "line": "1+ 3PM",
          "score": 71.9,
          "confidence": 72,
          "tier": "A",
          "reason": "Sample 12 | L10 70% | L5 60% | USG 30% | MIN 27.8 | 3PM matchup 1.07x | Prev 1.7 | Pre 0.0 | Decline 0.22"
        },
        {
          "player_id": "4898898",
          "player_name": "Gianna Kneepkens",
          "team": "CON",
          "opponent": "NY",
          "line": "1+ 3PM",
          "score": 68.35,
          "confidence": 68,
          "tier": "C",
          "reason": "Sample 2 | L10 100% | L5 100% | USG 15% | MIN 15.0 | 3PM matchup 1.07x | Prev 1.0 | Pre 1.0 | Minutes watch | Anti-correlation: same team as Saniya Rivers"
        }
      ]
    },
    "LADDERS": {
      "title": "Ladder Sleepers",
      "market": "LADDERS",
      "players": [
        {
          "player_id": "5105737",
          "player_name": "Lauren Betts",
          "team": "WSH",
          "opponent": "TOR",
          "line": "4+ REB",
          "score": 86.34,
          "confidence": 86,
          "tier": "B",
          "reason": "Sample 2 | L10 100% | L5 100% | USG 25% | MIN 24.5 | REB matchup 1.11x | Prev 4.5 | Pre 4.5",
          "market": "REB",
          "ladder": [
            "4+",
            "6+",
            "8+"
          ]
        },
        {
          "player_id": "2998928",
          "player_name": "Breanna Stewart",
          "team": "NY",
          "opponent": "CON",
          "line": "2+ AST",
          "score": 83.75,
          "confidence": 84,
          "tier": "A",
          "reason": "Sample 12 | L10 80% | L5 80% | USG 31% | MIN 25.4 | AST matchup 1.09x | Prev 2.4 | Pre 1.0 | Home boost",
          "market": "AST",
          "ladder": [
            "2+",
            "4+",
            "6+"
          ]
        },
        {
          "player_id": "4433514",
          "player_name": "Saniya Rivers",
          "team": "CON",
          "opponent": "NY",
          "line": "2+ AST",
          "score": 79.71,
          "confidence": 80,
          "tier": "B",
          "reason": "Sample 12 | L10 60% | L5 100% | USG 30% | MIN 27.8 | AST matchup 1.01x | Prev 2.4 | Pre 3.5 | Uptick 0.42",
          "market": "AST",
          "ladder": [
            "2+",
            "4+",
            "6+"
          ]
        },
        {
          "player_id": "2998928",
          "player_name": "Breanna Stewart",
          "team": "NY",
          "opponent": "CON",
          "line": "5+ REB",
          "score": 78.06,
          "confidence": 78,
          "tier": "B",
          "reason": "Sample 12 | L10 90% | L5 80% | USG 31% | MIN 25.4 | REB matchup 0.94x | Prev 6.3 | Pre 5.5 | Home boost",
          "market": "REB",
          "ladder": [
            "5+",
            "7+",
            "9+"
          ]
        },
        {
          "player_id": "4565505",
          "player_name": "Kiki Rice",
          "team": "TOR",
          "opponent": "WSH",
          "line": "2+ AST",
          "score": 77.94,
          "confidence": 78,
          "tier": "C",
          "reason": "Sample 2 | L10 100% | L5 100% | USG 20% | MIN 20.0 | AST matchup 1.05x | Prev 2.0 | Pre 2.0 | Home boost | Minutes watch",
          "market": "AST",
          "ladder": [
            "2+",
            "4+",
            "6+"
          ]
        }
      ]
    }
  },
  "pinned_board": {
    "title": "PTS Top 10",
    "market": "PTS",
    "players": [
      {
        "player_id": "4281930",
        "player_name": "Anneli Maley",
        "team": "NY",
        "opponent": "CON",
        "line": "13+ PTS",
        "score": 87.37,
        "confidence": 87,
        "tier": "B",
        "reason": "Sample 2 | L10 100% | L5 100% | USG 28% | MIN 27.0 | PTS matchup 1.05x | Prev 13.0 | Pre 13.0 | Home boost"
      },
      {
        "player_id": "4398935",
        "player_name": "Veronica Burton",
        "team": "GS",
        "opponent": "SEA",
        "line": "11+ PTS",
        "score": 73.26,
        "confidence": 73,
        "tier": "B",
        "reason": "Sample 12 | L10 70% | L5 80% | USG 45% | MIN 29.7 | PTS matchup 1.03x | Prev 13.0 | Pre 14.0"
      },
      {
        "player_id": "2998928",
        "player_name": "Breanna Stewart",
        "team": "NY",
        "opponent": "CON",
        "line": "14+ PTS",
        "score": 72.77,
        "confidence": 73,
        "tier": "A",
        "reason": "Sample 12 | L10 80% | L5 60% | USG 31% | MIN 25.4 | PTS matchup 1.05x | Prev 18.0 | Pre 10.0 | Home boost | Anti-correlation: same team as Anneli Maley"
      },
      {
        "player_id": "2988756",
        "player_name": "Brittney Sykes",
        "team": "TOR",
        "opponent": "WSH",
        "line": "8+ PTS",
        "score": 70.67,
        "confidence": 71,
        "tier": "B",
        "reason": "Sample 11 | L10 70% | L5 60% | USG 27% | MIN 24.6 | PTS matchup 1.03x | Prev 8.6 | Pre 8.0 | Decline 0.17 | Home boost"
      },
      {
        "player_id": "5345320",
        "player_name": "Pauline Astier",
        "team": "NY",
        "opponent": "CON",
        "line": "12+ PTS",
        "score": 70.02,
        "confidence": 70,
        "tier": "B",
        "reason": "Sample 1 | L10 100% | L5 100% | USG 18% | MIN 22.0 | PTS matchup 1.05x | Prev 12.0 | Pre 12.0 | Home boost | Minutes watch | Anti-correlation: same team as Anneli Maley"
      },
      {
        "player_id": "4790264",
        "player_name": "Janelle Salaun",
        "team": "GS",
        "opponent": "SEA",
        "line": "12+ PTS",
        "score": 69.77,
        "confidence": 70,
        "tier": "B",
        "reason": "Sample 11 | L10 60% | L5 80% | USG 38% | MIN 33.0 | PTS matchup 1.03x | Prev 13.8 | Pre 13.8 | Anti-correlation: same team as Veronica Burton"
      },
      {
        "player_id": "4583144",
        "player_name": "Cotie McMahon",
        "team": "WSH",
        "opponent": "TOR",
        "line": "9+ PTS",
        "score": 69.13,
        "confidence": 69,
        "tier": "B",
        "reason": "Sample 2 | L10 100% | L5 100% | USG 19% | MIN 25.0 | PTS matchup 0.98x | Prev 10.0 | Pre 10.0"
      },
      {
        "player_id": "4898384",
        "player_name": "Kiki Iriafen",
        "team": "WSH",
        "opponent": "TOR",
        "line": "13+ PTS",
        "score": 65.83,
        "confidence": 66,
        "tier": "B",
        "reason": "Sample 11 | L10 60% | L5 60% | USG 30% | MIN 25.4 | PTS matchup 0.98x | Prev 14.7 | Pre 11.0 | Uptick 0.13 | Anti-correlation: same team as Cotie McMahon"
      },
      {
        "player_id": "5220150",
        "player_name": "Dominique Malonga",
        "team": "SEA",
        "opponent": "GS",
        "line": "9+ PTS",
        "score": 63.52,
        "confidence": 64,
        "tier": "C",
        "reason": "Sample 11 | L10 60% | L5 80% | USG 25% | MIN 21.7 | PTS matchup 0.94x | Prev 9.9 | Pre 10.0 | Home boost | Minutes watch"
      },
      {
        "player_id": "4790263",
        "player_name": "Iliana Rupert",
        "team": "GS",
        "opponent": "SEA",
        "line": "8+ PTS",
        "score": 62.36,
        "confidence": 62,
        "tier": "B",
        "reason": "Sample 11 | L10 60% | L5 60% | USG 26% | MIN 25.7 | PTS matchup 1.03x | Prev 9.4 | Pre 9.4 | Decline 0.21 | Anti-correlation: same team as Veronica Burton"
      }
    ]
  },
  "games": [
    {
      "game_id": "401856890",
      "matchup": "CON @ NY",
      "time": "5/8 - 7:30 PM EDT",
      "top_signals": [
        {
          "market": "PTS",
          "player_id": "4281930",
          "player_name": "Anneli Maley",
          "line": "13+ PTS",
          "score": 87.37,
          "confidence": 87,
          "tier": "B"
        },
        {
          "market": "AST",
          "player_id": "2998928",
          "player_name": "Breanna Stewart",
          "line": "2+ AST",
          "score": 83.75,
          "confidence": 84,
          "tier": "A"
        },
        {
          "market": "3PM",
          "player_id": "4703579",
          "player_name": "Derin Erdogan",
          "line": "1+ 3PM",
          "score": 80.71,
          "confidence": 81,
          "tier": "C"
        }
      ],
      "markets": {
        "PTS": [
          {
            "player_id": "4281930",
            "player_name": "Anneli Maley",
            "team": "NY",
            "opponent": "CON",
            "line": "13+ PTS",
            "score": 87.37,
            "confidence": 87,
            "tier": "B",
            "reason": "Sample 2 | L10 100% | L5 100% | USG 28% | MIN 27.0 | PTS matchup 1.05x | Prev 13.0 | Pre 13.0 | Home boost"
          },
          {
            "player_id": "2998928",
            "player_name": "Breanna Stewart",
            "team": "NY",
            "opponent": "CON",
            "line": "14+ PTS",
            "score": 72.77,
            "confidence": 73,
            "tier": "A",
            "reason": "Sample 12 | L10 80% | L5 60% | USG 31% | MIN 25.4 | PTS matchup 1.05x | Prev 18.0 | Pre 10.0 | Home boost | Anti-correlation: same team as Anneli Maley"
          },
          {
            "player_id": "5345320",
            "player_name": "Pauline Astier",
            "team": "NY",
            "opponent": "CON",
            "line": "12+ PTS",
            "score": 70.02,
            "confidence": 70,
            "tier": "B",
            "reason": "Sample 1 | L10 100% | L5 100% | USG 18% | MIN 22.0 | PTS matchup 1.05x | Prev 12.0 | Pre 12.0 | Home boost | Minutes watch | Anti-correlation: same team as Anneli Maley"
          },
          {
            "player_id": "4337216",
            "player_name": "Han Xu",
            "team": "NY",
            "opponent": "CON",
            "line": "13+ PTS",
            "score": 55.58,
            "confidence": 56,
            "tier": "C",
            "reason": "Sample 2 | L10 50% | L5 50% | USG 25% | MIN 18.5 | PTS matchup 1.05x | Prev 12.0 | Pre 12.0 | Home boost | Minutes watch | Anti-correlation: same team as Anneli Maley"
          },
          {
            "player_id": "4703579",
            "player_name": "Derin Erdogan",
            "team": "NY",
            "opponent": "CON",
            "line": "10+ PTS",
            "score": 47.72,
            "confidence": 48,
            "tier": "C",
            "reason": "Sample 2 | L10 50% | L5 50% | USG 20% | MIN 16.0 | PTS matchup 1.05x | Prev 10.0 | Pre 10.0 | Home boost | Minutes watch | Anti-correlation: same team as Anneli Maley"
          },
          {
            "player_id": "4595823",
            "player_name": "Alex Fowler",
            "team": "NY",
            "opponent": "CON",
            "line": "8+ PTS",
            "score": 46.07,
            "confidence": 46,
            "tier": "C",
            "reason": "Sample 2 | L10 50% | L5 50% | USG 17% | MIN 19.0 | PTS matchup 1.05x | Prev 4.0 | Pre 4.0 | Home boost | Minutes watch | Anti-correlation: same team as Anneli Maley"
          },
          {
            "player_id": "2490553",
            "player_name": "Brittney Griner",
            "team": "CON",
            "opponent": "NY",
            "line": "11+ PTS",
            "score": 42.88,
            "confidence": 43,
            "tier": "C",
            "reason": "Sample 2 | L10 50% | L5 50% | USG 23% | MIN 18.5 | PTS matchup 0.97x | Prev 11.5 | Pre 11.5 | Minutes watch"
          },
          {
            "player_id": "4433635",
            "player_name": "Diamond Miller",
            "team": "CON",
            "opponent": "NY",
            "line": "8+ PTS",
            "score": 38.48,
            "confidence": 38,
            "tier": "C",
            "reason": "Sample 2 | L10 50% | L5 50% | USG 18% | MIN 17.0 | PTS matchup 0.97x | Prev 7.0 | Pre 7.0 | Minutes watch | Anti-correlation: same team as Brittney Griner"
          },
          {
            "player_id": "4703609",
            "player_name": "Charlisse Leger-Walker",
            "team": "CON",
            "opponent": "NY",
            "line": "8+ PTS",
            "score": 38.19,
            "confidence": 38,
            "tier": "C",
            "reason": "Sample 2 | L10 50% | L5 50% | USG 18% | MIN 19.0 | PTS matchup 0.97x | Prev 4.0 | Pre 4.0 | Minutes watch | Anti-correlation: same team as Brittney Griner"
          },
          {
            "player_id": "4898898",
            "player_name": "Gianna Kneepkens",
            "team": "CON",
            "opponent": "NY",
            "line": "8+ PTS",
            "score": 11.53,
            "confidence": 12,
            "tier": "C",
            "reason": "Sample 2 | L10 0% | L5 0% | USG 15% | MIN 15.0 | PTS matchup 0.97x | Prev 4.0 | Pre 4.0 | Minutes watch | Anti-correlation: same team as Brittney Griner"
          }
        ],
        "REB": [
          {
            "player_id": "2998928",
            "player_name": "Breanna Stewart",
            "team": "NY",
            "opponent": "CON",
            "line": "5+ REB",
            "score": 78.06,
            "confidence": 78,
            "tier": "B",
            "reason": "Sample 12 | L10 90% | L5 80% | USG 31% | MIN 25.4 | REB matchup 0.94x | Prev 6.3 | Pre 5.5 | Home boost"
          },
          {
            "player_id": "2490553",
            "player_name": "Brittney Griner",
            "team": "CON",
            "opponent": "NY",
            "line": "4+ REB",
            "score": 73.84,
            "confidence": 74,
            "tier": "C",
            "reason": "Sample 2 | L10 100% | L5 100% | USG 23% | MIN 18.5 | REB matchup 0.94x | Prev 4.5 | Pre 4.5 | Minutes watch"
          },
          {
            "player_id": "4684384",
            "player_name": "Aneesah Morrow",
            "team": "CON",
            "opponent": "NY",
            "line": "9+ REB",
            "score": 64.6,
            "confidence": 65,
            "tier": "B",
            "reason": "Sample 12 | L10 60% | L5 60% | USG 29% | MIN 24.2 | REB matchup 0.94x | Prev 9.3 | Pre 7.5 | Uptick 0.18 | Anti-correlation: same team as Brittney Griner"
          },
          {
            "player_id": "4281930",
            "player_name": "Anneli Maley",
            "team": "NY",
            "opponent": "CON",
            "line": "7+ REB",
            "score": 56.21,
            "confidence": 56,
            "tier": "C",
            "reason": "Sample 2 | L10 50% | L5 50% | USG 28% | MIN 27.0 | REB matchup 0.94x | Prev 6.5 | Pre 6.5 | Home boost | Anti-correlation: same team as Breanna Stewart"
          },
          {
            "player_id": "4398966",
            "player_name": "Olivia Nelson-Ododa",
            "team": "CON",
            "opponent": "NY",
            "line": "3+ REB",
            "score": 52.77,
            "confidence": 53,
            "tier": "C",
            "reason": "Sample 6 | L10 67% | L5 60% | USG 16% | MIN 12.1 | REB matchup 0.94x | Prev 2.5 | Pre 4.0 | Minutes watch | Anti-correlation: same team as Brittney Griner"
          },
          {
            "player_id": "4595823",
            "player_name": "Alex Fowler",
            "team": "NY",
            "opponent": "CON",
            "line": "3+ REB",
            "score": 47.91,
            "confidence": 48,
            "tier": "C",
            "reason": "Sample 2 | L10 50% | L5 50% | USG 17% | MIN 19.0 | REB matchup 0.94x | Prev 3.5 | Pre 3.5 | Home boost | Minutes watch | Anti-correlation: same team as Breanna Stewart"
          },
          {
            "player_id": "4433635",
            "player_name": "Diamond Miller",
            "team": "CON",
            "opponent": "NY",
            "line": "3+ REB",
            "score": 44.6,
            "confidence": 45,
            "tier": "C",
            "reason": "Sample 2 | L10 50% | L5 50% | USG 18% | MIN 17.0 | REB matchup 0.94x | Prev 2.5 | Pre 2.5 | Minutes watch | Anti-correlation: same team as Brittney Griner"
          },
          {
            "player_id": "5105732",
            "player_name": "Raegan Beers",
            "team": "CON",
            "opponent": "NY",
            "line": "3+ REB",
            "score": 40.49,
            "confidence": 40,
            "tier": "C",
            "reason": "Sample 2 | L10 50% | L5 50% | USG 14% | MIN 12.5 | REB matchup 0.94x | Prev 2.5 | Pre 2.5 | Minutes watch | Anti-correlation: same team as Brittney Griner"
          },
          {
            "player_id": "4337216",
            "player_name": "Han Xu",
            "team": "NY",
            "opponent": "CON",
            "line": "3+ REB",
            "score": 27.71,
            "confidence": 28,
            "tier": "C",
            "reason": "Sample 2 | L10 0% | L5 0% | USG 25% | MIN 18.5 | REB matchup 0.94x | Prev 1.5 | Pre 1.5 | Home boost | Minutes watch | Anti-correlation: same team as Breanna Stewart"
          },
          {
            "player_id": "4703579",
            "player_name": "Derin Erdogan",
            "team": "NY",
            "opponent": "CON",
            "line": "3+ REB",
            "score": 25.52,
            "confidence": 26,
            "tier": "C",
            "reason": "Sample 2 | L10 0% | L5 0% | USG 20% | MIN 16.0 | REB matchup 0.94x | Prev 0.0 | Pre 0.0 | Home boost | Minutes watch | Anti-correlation: same team as Breanna Stewart"
          }
        ],
        "AST": [
          {
            "player_id": "2998928",
            "player_name": "Breanna Stewart",
            "team": "NY",
            "opponent": "CON",
            "line": "2+ AST",
            "score": 83.75,
            "confidence": 84,
            "tier": "A",
            "reason": "Sample 12 | L10 80% | L5 80% | USG 31% | MIN 25.4 | AST matchup 1.09x | Prev 2.4 | Pre 1.0 | Home boost"
          },
          {
            "player_id": "4433514",
            "player_name": "Saniya Rivers",
            "team": "CON",
            "opponent": "NY",
            "line": "2+ AST",
            "score": 79.71,
            "confidence": 80,
            "tier": "B",
            "reason": "Sample 12 | L10 60% | L5 100% | USG 30% | MIN 27.8 | AST matchup 1.01x | Prev 2.4 | Pre 3.5 | Uptick 0.42"
          },
          {
            "player_id": "5345320",
            "player_name": "Pauline Astier",
            "team": "NY",
            "opponent": "CON",
            "line": "4+ AST",
            "score": 75.4,
            "confidence": 75,
            "tier": "B",
            "reason": "Sample 1 | L10 100% | L5 100% | USG 18% | MIN 22.0 | AST matchup 1.09x | Prev 4.0 | Pre 4.0 | Home boost | Minutes watch | Anti-correlation: same team as Breanna Stewart"
          },
          {
            "player_id": "2999101",
            "player_name": "Jonquel Jones",
            "team": "NY",
            "opponent": "CON",
            "line": "2+ AST",
            "score": 68.95,
            "confidence": 69,
            "tier": "B",
            "reason": "Sample 11 | L10 70% | L5 60% | USG 19% | MIN 24.9 | AST matchup 1.09x | Prev 3.1 | Pre 1.0 | Decline 0.30 | Home boost | Anti-correlation: same team as Breanna Stewart"
          },
          {
            "player_id": "4281930",
            "player_name": "Anneli Maley",
            "team": "NY",
            "opponent": "CON",
            "line": "2+ AST",
            "score": 63.58,
            "confidence": 64,
            "tier": "C",
            "reason": "Sample 2 | L10 50% | L5 50% | USG 28% | MIN 27.0 | AST matchup 1.09x | Prev 2.0 | Pre 2.0 | Home boost | Anti-correlation: same team as Breanna Stewart"
          },
          {
            "player_id": "2490553",
            "player_name": "Brittney Griner",
            "team": "CON",
            "opponent": "NY",
            "line": "2+ AST",
            "score": 47.57,
            "confidence": 48,
            "tier": "C",
            "reason": "Sample 2 | L10 50% | L5 50% | USG 23% | MIN 18.5 | AST matchup 1.01x | Prev 1.5 | Pre 1.5 | Minutes watch | Anti-correlation: same team as Saniya Rivers"
          },
          {
            "player_id": "4433635",
            "player_name": "Diamond Miller",
            "team": "CON",
            "opponent": "NY",
            "line": "2+ AST",
            "score": 44.08,
            "confidence": 44,
            "tier": "C",
            "reason": "Sample 2 | L10 50% | L5 50% | USG 18% | MIN 17.0 | AST matchup 1.01x | Prev 2.0 | Pre 2.0 | Minutes watch | Anti-correlation: same team as Saniya Rivers"
          },
          {
            "player_id": "4703609",
            "player_name": "Charlisse Leger-Walker",
            "team": "CON",
            "opponent": "NY",
            "line": "2+ AST",
            "score": 43.72,
            "confidence": 44,
            "tier": "C",
            "reason": "Sample 2 | L10 50% | L5 50% | USG 18% | MIN 19.0 | AST matchup 1.01x | Prev 2.0 | Pre 2.0 | Minutes watch | Anti-correlation: same team as Saniya Rivers"
          },
          {
            "player_id": "4898898",
            "player_name": "Gianna Kneepkens",
            "team": "CON",
            "opponent": "NY",
            "line": "2+ AST",
            "score": 40.97,
            "confidence": 41,
            "tier": "C",
            "reason": "Sample 2 | L10 50% | L5 50% | USG 15% | MIN 15.0 | AST matchup 1.01x | Prev 1.0 | Pre 1.0 | Minutes watch | Anti-correlation: same team as Saniya Rivers"
          },
          {
            "player_id": "5105732",
            "player_name": "Raegan Beers",
            "team": "CON",
            "opponent": "NY",
            "line": "2+ AST",
            "score": 39.98,
            "confidence": 40,
            "tier": "C",
            "reason": "Sample 2 | L10 50% | L5 50% | USG 14% | MIN 12.5 | AST matchup 1.01x | Prev 1.5 | Pre 1.5 | Minutes watch | Anti-correlation: same team as Saniya Rivers"
          }
        ],
        "3PM": [
          {
            "player_id": "4703579",
            "player_name": "Derin Erdogan",
            "team": "NY",
            "opponent": "CON",
            "line": "1+ 3PM",
            "score": 80.71,
            "confidence": 81,
            "tier": "C",
            "reason": "Sample 2 | L10 100% | L5 100% | USG 20% | MIN 16.0 | 3PM matchup 1.20x | Prev 1.0 | Pre 1.0 | Home boost | Minutes watch"
          },
          {
            "player_id": "2998928",
            "player_name": "Breanna Stewart",
            "team": "NY",
            "opponent": "CON",
            "line": "1+ 3PM",
            "score": 79.05,
            "confidence": 79,
            "tier": "A",
            "reason": "Sample 12 | L10 80% | L5 60% | USG 31% | MIN 25.4 | 3PM matchup 1.20x | Prev 1.0 | Pre 1.0 | Home boost | Anti-correlation: same team as Derin Erdogan"
          },
          {
            "player_id": "4433514",
            "player_name": "Saniya Rivers",
            "team": "CON",
            "opponent": "NY",
            "line": "1+ 3PM",
            "score": 71.9,
            "confidence": 72,
            "tier": "A",
            "reason": "Sample 12 | L10 70% | L5 60% | USG 30% | MIN 27.8 | 3PM matchup 1.07x | Prev 1.7 | Pre 0.0 | Decline 0.22"
          },
          {
            "player_id": "4898898",
            "player_name": "Gianna Kneepkens",
            "team": "CON",
            "opponent": "NY",
            "line": "1+ 3PM",
            "score": 68.35,
            "confidence": 68,
            "tier": "C",
            "reason": "Sample 2 | L10 100% | L5 100% | USG 15% | MIN 15.0 | 3PM matchup 1.07x | Prev 1.0 | Pre 1.0 | Minutes watch | Anti-correlation: same team as Saniya Rivers"
          },
          {
            "player_id": "4281930",
            "player_name": "Anneli Maley",
            "team": "NY",
            "opponent": "CON",
            "line": "1+ 3PM",
            "score": 65.15,
            "confidence": 65,
            "tier": "C",
            "reason": "Sample 2 | L10 50% | L5 50% | USG 28% | MIN 27.0 | 3PM matchup 1.20x | Prev 0.5 | Pre 0.5 | Home boost | Anti-correlation: same team as Derin Erdogan"
          },
          {
            "player_id": "4337216",
            "player_name": "Han Xu",
            "team": "NY",
            "opponent": "CON",
            "line": "1+ 3PM",
            "score": 61.15,
            "confidence": 61,
            "tier": "C",
            "reason": "Sample 2 | L10 50% | L5 50% | USG 25% | MIN 18.5 | 3PM matchup 1.20x | Prev 0.5 | Pre 0.5 | Home boost | Minutes watch | Anti-correlation: same team as Derin Erdogan"
          },
          {
            "player_id": "2490553",
            "player_name": "Brittney Griner",
            "team": "CON",
            "opponent": "NY",
            "line": "1+ 3PM",
            "score": 50.46,
            "confidence": 50,
            "tier": "C",
            "reason": "Sample 2 | L10 50% | L5 50% | USG 23% | MIN 18.5 | 3PM matchup 1.07x | Prev 1.0 | Pre 1.0 | Minutes watch | Anti-correlation: same team as Saniya Rivers"
          },
          {
            "player_id": "5105732",
            "player_name": "Raegan Beers",
            "team": "CON",
            "opponent": "NY",
            "line": "1+ 3PM",
            "score": 42.86,
            "confidence": 43,
            "tier": "C",
            "reason": "Sample 2 | L10 50% | L5 50% | USG 14% | MIN 12.5 | 3PM matchup 1.07x | Prev 0.5 | Pre 0.5 | Minutes watch | Anti-correlation: same team as Saniya Rivers"
          },
          {
            "player_id": "4595823",
            "player_name": "Alex Fowler",
            "team": "NY",
            "opponent": "CON",
            "line": "1+ 3PM",
            "score": 28.34,
            "confidence": 28,
            "tier": "C",
            "reason": "Sample 2 | L10 0% | L5 0% | USG 17% | MIN 19.0 | 3PM matchup 1.20x | Prev 0.0 | Pre 0.0 | Home boost | Minutes watch | Anti-correlation: same team as Derin Erdogan"
          },
          {
            "player_id": "5345320",
            "player_name": "Pauline Astier",
            "team": "NY",
            "opponent": "CON",
            "line": "1+ 3PM",
            "score": 27.97,
            "confidence": 28,
            "tier": "C",
            "reason": "Sample 1 | L10 0% | L5 0% | USG 18% | MIN 22.0 | 3PM matchup 1.20x | Prev 0.0 | Pre 0.0 | Home boost | Minutes watch | Anti-correlation: same team as Derin Erdogan"
          }
        ],
        "ML": [
          {
            "player_id": "ny-moneyline",
            "player_name": "NY",
            "team": "NY",
            "opponent": "CON",
            "line": "Moneyline",
            "score": 61.67,
            "confidence": 62,
            "tier": "C",
            "reason": "Recent win 58% | Allow 77.2 PPG"
          }
        ]
      }
    },
    {
      "game_id": "401856891",
      "matchup": "WSH @ TOR",
      "time": "5/8 - 7:30 PM EDT",
      "top_signals": [
        {
          "market": "REB",
          "player_id": "5105737",
          "player_name": "Lauren Betts",
          "line": "4+ REB",
          "score": 86.34,
          "confidence": 86,
          "tier": "B"
        },
        {
          "market": "3PM",
          "player_id": "3142327",
          "player_name": "Kia Nurse",
          "line": "1+ 3PM",
          "score": 81.29,
          "confidence": 81,
          "tier": "C"
        },
        {
          "market": "AST",
          "player_id": "4565505",
          "player_name": "Kiki Rice",
          "line": "2+ AST",
          "score": 77.94,
          "confidence": 78,
          "tier": "C"
        }
      ],
      "markets": {
        "PTS": [
          {
            "player_id": "2988756",
            "player_name": "Brittney Sykes",
            "team": "TOR",
            "opponent": "WSH",
            "line": "8+ PTS",
            "score": 70.67,
            "confidence": 71,
            "tier": "B",
            "reason": "Sample 11 | L10 70% | L5 60% | USG 27% | MIN 24.6 | PTS matchup 1.03x | Prev 8.6 | Pre 8.0 | Decline 0.17 | Home boost"
          },
          {
            "player_id": "4583144",
            "player_name": "Cotie McMahon",
            "team": "WSH",
            "opponent": "TOR",
            "line": "9+ PTS",
            "score": 69.13,
            "confidence": 69,
            "tier": "B",
            "reason": "Sample 2 | L10 100% | L5 100% | USG 19% | MIN 25.0 | PTS matchup 0.98x | Prev 10.0 | Pre 10.0"
          },
          {
            "player_id": "4898384",
            "player_name": "Kiki Iriafen",
            "team": "WSH",
            "opponent": "TOR",
            "line": "13+ PTS",
            "score": 65.83,
            "confidence": 66,
            "tier": "B",
            "reason": "Sample 11 | L10 60% | L5 60% | USG 30% | MIN 25.4 | PTS matchup 0.98x | Prev 14.7 | Pre 11.0 | Uptick 0.13 | Anti-correlation: same team as Cotie McMahon"
          },
          {
            "player_id": "4433524",
            "player_name": "Sonia Citron",
            "team": "WSH",
            "opponent": "TOR",
            "line": "10+ PTS",
            "score": 57.91,
            "confidence": 58,
            "tier": "B",
            "reason": "Sample 12 | L10 80% | L5 60% | USG 23% | MIN 28.0 | PTS matchup 0.98x | Prev 13.9 | Pre 9.0 | Decline 0.13 | Anti-correlation: same team as Cotie McMahon"
          },
          {
            "player_id": "5345444",
            "player_name": "Laura Juskaite",
            "team": "TOR",
            "opponent": "WSH",
            "line": "8+ PTS",
            "score": 56.53,
            "confidence": 57,
            "tier": "C",
            "reason": "Sample 2 | L10 50% | L5 50% | USG 32% | MIN 23.5 | PTS matchup 1.03x | Prev 8.0 | Pre 8.0 | Home boost | Minutes watch | Anti-correlation: same team as Brittney Sykes"
          },
          {
            "player_id": "4399342",
            "player_name": "Lexi Held",
            "team": "TOR",
            "opponent": "WSH",
            "line": "14+ PTS",
            "score": 54.7,
            "confidence": 55,
            "tier": "C",
            "reason": "Sample 2 | L10 50% | L5 50% | USG 25% | MIN 22.5 | PTS matchup 1.03x | Prev 13.0 | Pre 13.0 | Home boost | Minutes watch | Anti-correlation: same team as Brittney Sykes"
          },
          {
            "player_id": "5105737",
            "player_name": "Lauren Betts",
            "team": "WSH",
            "opponent": "TOR",
            "line": "15+ PTS",
            "score": 51.91,
            "confidence": 52,
            "tier": "C",
            "reason": "Sample 2 | L10 50% | L5 50% | USG 25% | MIN 24.5 | PTS matchup 0.98x | Prev 15.0 | Pre 15.0 | Anti-correlation: same team as Cotie McMahon"
          },
          {
            "player_id": "3142327",
            "player_name": "Kia Nurse",
            "team": "TOR",
            "opponent": "WSH",
            "line": "8+ PTS",
            "score": 48.21,
            "confidence": 48,
            "tier": "C",
            "reason": "Sample 2 | L10 50% | L5 50% | USG 22% | MIN 16.5 | PTS matchup 1.03x | Prev 7.5 | Pre 7.5 | Home boost | Minutes watch | Anti-correlation: same team as Brittney Sykes"
          },
          {
            "player_id": "4565505",
            "player_name": "Kiki Rice",
            "team": "TOR",
            "opponent": "WSH",
            "line": "8+ PTS",
            "score": 46.91,
            "confidence": 47,
            "tier": "C",
            "reason": "Sample 2 | L10 50% | L5 50% | USG 20% | MIN 20.0 | PTS matchup 1.03x | Prev 7.5 | Pre 7.5 | Home boost | Minutes watch | Anti-correlation: same team as Brittney Sykes"
          },
          {
            "player_id": "5122345",
            "player_name": "Cassandre Prosper",
            "team": "WSH",
            "opponent": "TOR",
            "line": "8+ PTS",
            "score": 36.91,
            "confidence": 37,
            "tier": "C",
            "reason": "Sample 2 | L10 50% | L5 50% | USG 15% | MIN 19.5 | PTS matchup 0.98x | Prev 6.0 | Pre 6.0 | Minutes watch | Anti-correlation: same team as Cotie McMahon"
          }
        ],
        "REB": [
          {
            "player_id": "5105737",
            "player_name": "Lauren Betts",
            "team": "WSH",
            "opponent": "TOR",
            "line": "4+ REB",
            "score": 86.34,
            "confidence": 86,
            "tier": "B",
            "reason": "Sample 2 | L10 100% | L5 100% | USG 25% | MIN 24.5 | REB matchup 1.11x | Prev 4.5 | Pre 4.5"
          },
          {
            "player_id": "4433411",
            "player_name": "Angela Dugalic",
            "team": "WSH",
            "opponent": "TOR",
            "line": "5+ REB",
            "score": 76.08,
            "confidence": 76,
            "tier": "C",
            "reason": "Sample 2 | L10 100% | L5 100% | USG 16% | MIN 20.0 | REB matchup 1.11x | Prev 5.5 | Pre 5.5 | Minutes watch | Anti-correlation: same team as Lauren Betts"
          },
          {
            "player_id": "5122345",
            "player_name": "Cassandre Prosper",
            "team": "WSH",
            "opponent": "TOR",
            "line": "3+ REB",
            "score": 74.94,
            "confidence": 75,
            "tier": "C",
            "reason": "Sample 2 | L10 100% | L5 100% | USG 15% | MIN 19.5 | REB matchup 1.11x | Prev 4.0 | Pre 4.0 | Minutes watch | Anti-correlation: same team as Lauren Betts"
          },
          {
            "player_id": "4001679",
            "player_name": "Julie Allemand",
            "team": "TOR",
            "opponent": "WSH",
            "line": "6+ REB",
            "score": 68.03,
            "confidence": 68,
            "tier": "B",
            "reason": "Sample 1 | L10 100% | L5 100% | USG 7% | MIN 22.0 | REB matchup 1.04x | Prev 6.0 | Pre 6.0 | Home boost | Minutes watch"
          },
          {
            "player_id": "2988756",
            "player_name": "Brittney Sykes",
            "team": "TOR",
            "opponent": "WSH",
            "line": "3+ REB",
            "score": 64.92,
            "confidence": 65,
            "tier": "B",
            "reason": "Sample 11 | L10 60% | L5 40% | USG 27% | MIN 24.6 | REB matchup 1.04x | Prev 2.8 | Pre 1.0 | Home boost | Anti-correlation: same team as Julie Allemand"
          },
          {
            "player_id": "4583144",
            "player_name": "Cotie McMahon",
            "team": "WSH",
            "opponent": "TOR",
            "line": "3+ REB",
            "score": 57.59,
            "confidence": 58,
            "tier": "C",
            "reason": "Sample 2 | L10 50% | L5 50% | USG 19% | MIN 25.0 | REB matchup 1.11x | Prev 2.0 | Pre 2.0 | Anti-correlation: same team as Lauren Betts"
          },
          {
            "player_id": "5345444",
            "player_name": "Laura Juskaite",
            "team": "TOR",
            "opponent": "WSH",
            "line": "5+ REB",
            "score": 57.14,
            "confidence": 57,
            "tier": "C",
            "reason": "Sample 2 | L10 50% | L5 50% | USG 32% | MIN 23.5 | REB matchup 1.04x | Prev 5.5 | Pre 5.5 | Home boost | Minutes watch | Anti-correlation: same team as Julie Allemand"
          },
          {
            "player_id": "4434020",
            "player_name": "Teonni Key",
            "team": "TOR",
            "opponent": "WSH",
            "line": "3+ REB",
            "score": 49.57,
            "confidence": 50,
            "tier": "C",
            "reason": "Sample 2 | L10 50% | L5 50% | USG 14% | MIN 20.0 | REB matchup 1.04x | Prev 3.5 | Pre 3.5 | Home boost | Minutes watch | Anti-correlation: same team as Julie Allemand"
          },
          {
            "player_id": "4597509",
            "player_name": "Aaliyah Nye",
            "team": "TOR",
            "opponent": "WSH",
            "line": "3+ REB",
            "score": 49.1,
            "confidence": 49,
            "tier": "C",
            "reason": "Sample 2 | L10 50% | L5 50% | USG 13% | MIN 18.5 | REB matchup 1.04x | Prev 1.5 | Pre 1.5 | Home boost | Minutes watch | Anti-correlation: same team as Julie Allemand"
          },
          {
            "player_id": "5106145",
            "player_name": "Darianna Littlepage-Buggs",
            "team": "WSH",
            "opponent": "TOR",
            "line": "3+ REB",
            "score": 44.77,
            "confidence": 45,
            "tier": "C",
            "reason": "Sample 2 | L10 50% | L5 50% | USG 9% | MIN 12.0 | REB matchup 1.11x | Prev 2.5 | Pre 2.5 | Minutes watch | Anti-correlation: same team as Lauren Betts"
          }
        ],
        "AST": [
          {
            "player_id": "4565505",
            "player_name": "Kiki Rice",
            "team": "TOR",
            "opponent": "WSH",
            "line": "2+ AST",
            "score": 77.94,
            "confidence": 78,
            "tier": "C",
            "reason": "Sample 2 | L10 100% | L5 100% | USG 20% | MIN 20.0 | AST matchup 1.05x | Prev 2.0 | Pre 2.0 | Home boost | Minutes watch"
          },
          {
            "player_id": "2569044",
            "player_name": "Temi Fagbenle",
            "team": "TOR",
            "opponent": "WSH",
            "line": "2+ AST",
            "score": 65.74,
            "confidence": 66,
            "tier": "B",
            "reason": "Sample 12 | L10 60% | L5 60% | USG 20% | MIN 24.4 | AST matchup 1.05x | Prev 1.5 | Pre 2.0 | Home boost | Anti-correlation: same team as Kiki Rice"
          },
          {
            "player_id": "4001679",
            "player_name": "Julie Allemand",
            "team": "TOR",
            "opponent": "WSH",
            "line": "2+ AST",
            "score": 63.53,
            "confidence": 64,
            "tier": "B",
            "reason": "Sample 1 | L10 100% | L5 100% | USG 7% | MIN 22.0 | AST matchup 1.05x | Prev 2.0 | Pre 2.0 | Home boost | Minutes watch | Anti-correlation: same team as Kiki Rice"
          },
          {
            "player_id": "2988756",
            "player_name": "Brittney Sykes",
            "team": "TOR",
            "opponent": "WSH",
            "line": "2+ AST",
            "score": 62.89,
            "confidence": 63,
            "tier": "B",
            "reason": "Sample 11 | L10 60% | L5 20% | USG 27% | MIN 24.6 | AST matchup 1.05x | Prev 2.1 | Pre 0.0 | Decline 0.37 | Home boost | Anti-correlation: same team as Kiki Rice"
          },
          {
            "player_id": "4704180",
            "player_name": "Georgia Amoore",
            "team": "WSH",
            "opponent": "TOR",
            "line": "2+ AST",
            "score": 60.63,
            "confidence": 61,
            "tier": "C",
            "reason": "Sample 2 | L10 100% | L5 100% | USG 13% | MIN 15.0 | AST matchup 0.86x | Prev 2.0 | Pre 2.0 | Minutes watch"
          },
          {
            "player_id": "4399342",
            "player_name": "Lexi Held",
            "team": "TOR",
            "opponent": "WSH",
            "line": "2+ AST",
            "score": 57.89,
            "confidence": 58,
            "tier": "C",
            "reason": "Sample 2 | L10 50% | L5 50% | USG 25% | MIN 22.5 | AST matchup 1.05x | Prev 1.0 | Pre 1.0 | Home boost | Minutes watch | Anti-correlation: same team as Kiki Rice"
          },
          {
            "player_id": "5345444",
            "player_name": "Laura Juskaite",
            "team": "TOR",
            "opponent": "WSH",
            "line": "2+ AST",
            "score": 57.89,
            "confidence": 58,
            "tier": "C",
            "reason": "Sample 2 | L10 50% | L5 50% | USG 32% | MIN 23.5 | AST matchup 1.05x | Prev 1.5 | Pre 1.5 | Home boost | Minutes watch | Anti-correlation: same team as Kiki Rice"
          },
          {
            "player_id": "4433524",
            "player_name": "Sonia Citron",
            "team": "WSH",
            "opponent": "TOR",
            "line": "2+ AST",
            "score": 55.98,
            "confidence": 56,
            "tier": "B",
            "reason": "Sample 12 | L10 60% | L5 60% | USG 23% | MIN 28.0 | AST matchup 0.86x | Prev 2.0 | Pre 2.5 | Anti-correlation: same team as Georgia Amoore"
          },
          {
            "player_id": "5105737",
            "player_name": "Lauren Betts",
            "team": "WSH",
            "opponent": "TOR",
            "line": "2+ AST",
            "score": 51.15,
            "confidence": 51,
            "tier": "C",
            "reason": "Sample 2 | L10 50% | L5 50% | USG 25% | MIN 24.5 | AST matchup 0.86x | Prev 2.0 | Pre 2.0 | Anti-correlation: same team as Georgia Amoore"
          },
          {
            "player_id": "4434020",
            "player_name": "Teonni Key",
            "team": "TOR",
            "opponent": "WSH",
            "line": "2+ AST",
            "score": 46.32,
            "confidence": 46,
            "tier": "C",
            "reason": "Sample 2 | L10 50% | L5 50% | USG 14% | MIN 20.0 | AST matchup 1.05x | Prev 1.0 | Pre 1.0 | Home boost | Minutes watch | Anti-correlation: same team as Kiki Rice"
          }
        ],
        "3PM": [
          {
            "player_id": "3142327",
            "player_name": "Kia Nurse",
            "team": "TOR",
            "opponent": "WSH",
            "line": "1+ 3PM",
            "score": 81.29,
            "confidence": 81,
            "tier": "C",
            "reason": "Sample 2 | L10 100% | L5 100% | USG 22% | MIN 16.5 | 3PM matchup 1.09x | Prev 1.5 | Pre 1.5 | Home boost | Minutes watch"
          },
          {
            "player_id": "4597509",
            "player_name": "Aaliyah Nye",
            "team": "TOR",
            "opponent": "WSH",
            "line": "1+ 3PM",
            "score": 72.05,
            "confidence": 72,
            "tier": "C",
            "reason": "Sample 2 | L10 100% | L5 100% | USG 13% | MIN 18.5 | 3PM matchup 1.09x | Prev 1.5 | Pre 1.5 | Home boost | Minutes watch | Anti-correlation: same team as Kia Nurse"
          },
          {
            "player_id": "4433524",
            "player_name": "Sonia Citron",
            "team": "WSH",
            "opponent": "TOR",
            "line": "1+ 3PM",
            "score": 67.25,
            "confidence": 67,
            "tier": "B",
            "reason": "Sample 12 | L10 80% | L5 80% | USG 23% | MIN 28.0 | 3PM matchup 0.75x | Prev 2.2 | Pre 1.0 | Decline 0.16"
          },
          {
            "player_id": "4001679",
            "player_name": "Julie Allemand",
            "team": "TOR",
            "opponent": "WSH",
            "line": "1+ 3PM",
            "score": 65.23,
            "confidence": 65,
            "tier": "B",
            "reason": "Sample 1 | L10 100% | L5 100% | USG 7% | MIN 22.0 | 3PM matchup 1.09x | Prev 1.0 | Pre 1.0 | Home boost | Minutes watch | Anti-correlation: same team as Kia Nurse"
          },
          {
            "player_id": "4399342",
            "player_name": "Lexi Held",
            "team": "TOR",
            "opponent": "WSH",
            "line": "3+ 3PM",
            "score": 59.59,
            "confidence": 60,
            "tier": "C",
            "reason": "Sample 2 | L10 50% | L5 50% | USG 25% | MIN 22.5 | 3PM matchup 1.09x | Prev 3.0 | Pre 3.0 | Home boost | Minutes watch | Anti-correlation: same team as Kia Nurse"
          },
          {
            "player_id": "4704180",
            "player_name": "Georgia Amoore",
            "team": "WSH",
            "opponent": "TOR",
            "line": "1+ 3PM",
            "score": 59.38,
            "confidence": 59,
            "tier": "C",
            "reason": "Sample 2 | L10 100% | L5 100% | USG 13% | MIN 15.0 | 3PM matchup 0.75x | Prev 1.5 | Pre 1.5 | Minutes watch | Anti-correlation: same team as Sonia Citron"
          },
          {
            "player_id": "4565505",
            "player_name": "Kiki Rice",
            "team": "TOR",
            "opponent": "WSH",
            "line": "1+ 3PM",
            "score": 53.89,
            "confidence": 54,
            "tier": "C",
            "reason": "Sample 2 | L10 50% | L5 50% | USG 20% | MIN 20.0 | 3PM matchup 1.09x | Prev 0.5 | Pre 0.5 | Home boost | Minutes watch | Anti-correlation: same team as Kia Nurse"
          },
          {
            "player_id": "4583144",
            "player_name": "Cotie McMahon",
            "team": "WSH",
            "opponent": "TOR",
            "line": "1+ 3PM",
            "score": 44.15,
            "confidence": 44,
            "tier": "C",
            "reason": "Sample 2 | L10 50% | L5 50% | USG 19% | MIN 25.0 | 3PM matchup 0.75x | Prev 0.5 | Pre 0.5 | Anti-correlation: same team as Sonia Citron"
          },
          {
            "player_id": "4433411",
            "player_name": "Angela Dugalic",
            "team": "WSH",
            "opponent": "TOR",
            "line": "1+ 3PM",
            "score": 38.14,
            "confidence": 38,
            "tier": "C",
            "reason": "Sample 2 | L10 50% | L5 50% | USG 16% | MIN 20.0 | 3PM matchup 0.75x | Prev 0.5 | Pre 0.5 | Minutes watch | Anti-correlation: same team as Sonia Citron"
          },
          {
            "player_id": "5122345",
            "player_name": "Cassandre Prosper",
            "team": "WSH",
            "opponent": "TOR",
            "line": "1+ 3PM",
            "score": 37.0,
            "confidence": 37,
            "tier": "C",
            "reason": "Sample 2 | L10 50% | L5 50% | USG 15% | MIN 19.5 | 3PM matchup 0.75x | Prev 0.5 | Pre 0.5 | Minutes watch | Anti-correlation: same team as Sonia Citron"
          }
        ],
        "ML": [
          {
            "player_id": "tor-moneyline",
            "player_name": "TOR",
            "team": "TOR",
            "opponent": "WSH",
            "line": "Moneyline",
            "score": 34.0,
            "confidence": 34,
            "tier": "C",
            "reason": "Recent win 0% | Allow 78.0 PPG"
          }
        ]
      }
    },
    {
      "game_id": "401856892",
      "matchup": "GS @ SEA",
      "time": "5/8 - 10:00 PM EDT",
      "top_signals": [
        {
          "market": "3PM",
          "player_id": "4066527",
          "player_name": "Jaelyn Brown",
          "line": "1+ 3PM",
          "score": 79.25,
          "confidence": 79,
          "tier": "C"
        },
        {
          "market": "REB",
          "player_id": "4698736",
          "player_name": "Flau'jae Johnson",
          "line": "3+ REB",
          "score": 77.72,
          "confidence": 78,
          "tier": "C"
        },
        {
          "market": "REB",
          "player_id": "4790264",
          "player_name": "Janelle Salaun",
          "line": "6+ REB",
          "score": 77.19,
          "confidence": 77,
          "tier": "B"
        }
      ],
      "markets": {
        "PTS": [
          {
            "player_id": "4398935",
            "player_name": "Veronica Burton",
            "team": "GS",
            "opponent": "SEA",
            "line": "11+ PTS",
            "score": 73.26,
            "confidence": 73,
            "tier": "B",
            "reason": "Sample 12 | L10 70% | L5 80% | USG 45% | MIN 29.7 | PTS matchup 1.03x | Prev 13.0 | Pre 14.0"
          },
          {
            "player_id": "4790264",
            "player_name": "Janelle Salaun",
            "team": "GS",
            "opponent": "SEA",
            "line": "12+ PTS",
            "score": 69.77,
            "confidence": 70,
            "tier": "B",
            "reason": "Sample 11 | L10 60% | L5 80% | USG 38% | MIN 33.0 | PTS matchup 1.03x | Prev 13.8 | Pre 13.8 | Anti-correlation: same team as Veronica Burton"
          },
          {
            "player_id": "5220150",
            "player_name": "Dominique Malonga",
            "team": "SEA",
            "opponent": "GS",
            "line": "9+ PTS",
            "score": 63.52,
            "confidence": 64,
            "tier": "C",
            "reason": "Sample 11 | L10 60% | L5 80% | USG 25% | MIN 21.7 | PTS matchup 0.94x | Prev 9.9 | Pre 10.0 | Home boost | Minutes watch"
          },
          {
            "player_id": "4790263",
            "player_name": "Iliana Rupert",
            "team": "GS",
            "opponent": "SEA",
            "line": "8+ PTS",
            "score": 62.36,
            "confidence": 62,
            "tier": "B",
            "reason": "Sample 11 | L10 60% | L5 60% | USG 26% | MIN 25.7 | PTS matchup 1.03x | Prev 9.4 | Pre 9.4 | Decline 0.21 | Anti-correlation: same team as Veronica Burton"
          },
          {
            "player_id": "4698736",
            "player_name": "Flau'jae Johnson",
            "team": "SEA",
            "opponent": "GS",
            "line": "17+ PTS",
            "score": 52.2,
            "confidence": 52,
            "tier": "C",
            "reason": "Sample 2 | L10 50% | L5 50% | USG 35% | MIN 21.0 | PTS matchup 0.94x | Prev 16.0 | Pre 16.0 | Home boost | Minutes watch | Anti-correlation: same team as Dominique Malonga"
          },
          {
            "player_id": "4066527",
            "player_name": "Jaelyn Brown",
            "team": "SEA",
            "opponent": "GS",
            "line": "8+ PTS",
            "score": 41.05,
            "confidence": 41,
            "tier": "C",
            "reason": "Sample 2 | L10 50% | L5 50% | USG 18% | MIN 12.0 | PTS matchup 0.94x | Prev 7.0 | Pre 7.0 | Home boost | Minutes watch | Anti-correlation: same team as Dominique Malonga"
          },
          {
            "player_id": "2529622",
            "player_name": "Kayla Thornton",
            "team": "GS",
            "opponent": "SEA",
            "line": "8+ PTS",
            "score": 19.86,
            "confidence": 20,
            "tier": "C",
            "reason": "Sample 1 | L10 0% | L5 0% | USG 23% | MIN 15.0 | PTS matchup 1.03x | Prev 7.0 | Pre 7.0 | Minutes watch | Anti-correlation: same team as Veronica Burton"
          },
          {
            "player_id": "1054",
            "player_name": "Tiffany Hayes",
            "team": "GS",
            "opponent": "SEA",
            "line": "8+ PTS",
            "score": 15.85,
            "confidence": 16,
            "tier": "C",
            "reason": "Sample 2 | L10 0% | L5 0% | USG 16% | MIN 15.5 | PTS matchup 1.03x | Prev 5.0 | Pre 5.0 | Minutes watch | Anti-correlation: same team as Veronica Burton"
          },
          {
            "player_id": "3906753",
            "player_name": "Natisha Hiedeman",
            "team": "SEA",
            "opponent": "GS",
            "line": "8+ PTS",
            "score": 13.12,
            "confidence": 13,
            "tier": "C",
            "reason": "Sample 1 | L10 0% | L5 0% | USG 15% | MIN 14.0 | PTS matchup 0.94x | Prev 0.0 | Pre 0.0 | Home boost | Minutes watch | Anti-correlation: same team as Dominique Malonga"
          },
          {
            "player_id": "4280888",
            "player_name": "Rennia Davis",
            "team": "SEA",
            "opponent": "GS",
            "line": "8+ PTS",
            "score": 12.05,
            "confidence": 12,
            "tier": "C",
            "reason": "Sample 2 | L10 0% | L5 0% | USG 12% | MIN 8.5 | PTS matchup 0.94x | Prev 6.5 | Pre 6.5 | Home boost | Minutes watch | Anti-correlation: same team as Dominique Malonga"
          }
        ],
        "REB": [
          {
            "player_id": "4698736",
            "player_name": "Flau'jae Johnson",
            "team": "SEA",
            "opponent": "GS",
            "line": "3+ REB",
            "score": 77.72,
            "confidence": 78,
            "tier": "C",
            "reason": "Sample 2 | L10 100% | L5 100% | USG 35% | MIN 21.0 | REB matchup 0.94x | Prev 3.5 | Pre 3.5 | Home boost | Minutes watch"
          },
          {
            "player_id": "4790264",
            "player_name": "Janelle Salaun",
            "team": "GS",
            "opponent": "SEA",
            "line": "6+ REB",
            "score": 77.19,
            "confidence": 77,
            "tier": "B",
            "reason": "Sample 11 | L10 70% | L5 80% | USG 38% | MIN 33.0 | REB matchup 1.03x | Prev 5.9 | Pre 5.9 | Uptick 0.18"
          },
          {
            "player_id": "4398935",
            "player_name": "Veronica Burton",
            "team": "GS",
            "opponent": "SEA",
            "line": "3+ REB",
            "score": 69.6,
            "confidence": 70,
            "tier": "B",
            "reason": "Sample 12 | L10 80% | L5 60% | USG 45% | MIN 29.7 | REB matchup 1.03x | Prev 5.1 | Pre 1.0 | Decline 0.16 | Anti-correlation: same team as Janelle Salaun"
          },
          {
            "player_id": "2590093",
            "player_name": "Kiah Stokes",
            "team": "GS",
            "opponent": "SEA",
            "line": "5+ REB",
            "score": 64.15,
            "confidence": 64,
            "tier": "C",
            "reason": "Sample 1 | L10 100% | L5 100% | USG 9% | MIN 10.0 | REB matchup 1.03x | Prev 5.0 | Pre 5.0 | Minutes watch | Anti-correlation: same team as Janelle Salaun"
          },
          {
            "player_id": "4432834",
            "player_name": "Laeticia Amihere",
            "team": "GS",
            "opponent": "SEA",
            "line": "3+ REB",
            "score": 54.1,
            "confidence": 54,
            "tier": "C",
            "reason": "Sample 8 | L10 62% | L5 60% | USG 13% | MIN 9.8 | REB matchup 1.03x | Prev 3.7 | Pre 4.0 | Decline 0.15 | Minutes watch | Anti-correlation: same team as Janelle Salaun"
          },
          {
            "player_id": "4280888",
            "player_name": "Rennia Davis",
            "team": "SEA",
            "opponent": "GS",
            "line": "3+ REB",
            "score": 42.6,
            "confidence": 43,
            "tier": "C",
            "reason": "Sample 2 | L10 50% | L5 50% | USG 12% | MIN 8.5 | REB matchup 0.94x | Prev 3.0 | Pre 3.0 | Home boost | Minutes watch | Anti-correlation: same team as Flau'jae Johnson"
          },
          {
            "player_id": "5105731",
            "player_name": "Grace VanSlooten",
            "team": "SEA",
            "opponent": "GS",
            "line": "3+ REB",
            "score": 38.32,
            "confidence": 38,
            "tier": "C",
            "reason": "Sample 2 | L10 50% | L5 50% | USG 7% | MIN 15.0 | REB matchup 0.94x | Prev 2.0 | Pre 2.0 | Home boost | Minutes watch | Anti-correlation: same team as Flau'jae Johnson"
          },
          {
            "player_id": "2529622",
            "player_name": "Kayla Thornton",
            "team": "GS",
            "opponent": "SEA",
            "line": "3+ REB",
            "score": 27.2,
            "confidence": 27,
            "tier": "C",
            "reason": "Sample 1 | L10 0% | L5 0% | USG 23% | MIN 15.0 | REB matchup 1.03x | Prev 1.0 | Pre 1.0 | Minutes watch | Anti-correlation: same team as Janelle Salaun"
          },
          {
            "player_id": "1054",
            "player_name": "Tiffany Hayes",
            "team": "GS",
            "opponent": "SEA",
            "line": "3+ REB",
            "score": 24.97,
            "confidence": 25,
            "tier": "C",
            "reason": "Sample 2 | L10 0% | L5 0% | USG 16% | MIN 15.5 | REB matchup 1.03x | Prev 1.0 | Pre 0.0 | Decline 0.25 | Minutes watch | Anti-correlation: same team as Janelle Salaun"
          },
          {
            "player_id": "4066527",
            "player_name": "Jaelyn Brown",
            "team": "SEA",
            "opponent": "GS",
            "line": "3+ REB",
            "score": 23.82,
            "confidence": 24,
            "tier": "C",
            "reason": "Sample 2 | L10 0% | L5 0% | USG 18% | MIN 12.0 | REB matchup 0.94x | Prev 1.0 | Pre 1.0 | Home boost | Minutes watch | Anti-correlation: same team as Flau'jae Johnson"
          }
        ],
        "AST": [
          {
            "player_id": "4398935",
            "player_name": "Veronica Burton",
            "team": "GS",
            "opponent": "SEA",
            "line": "7+ AST",
            "score": 68.73,
            "confidence": 69,
            "tier": "B",
            "reason": "Sample 12 | L10 60% | L5 80% | USG 45% | MIN 29.7 | AST matchup 1.00x | Prev 8.5 | Pre 3.0"
          },
          {
            "player_id": "3906753",
            "player_name": "Natisha Hiedeman",
            "team": "SEA",
            "opponent": "GS",
            "line": "3+ AST",
            "score": 68.37,
            "confidence": 68,
            "tier": "C",
            "reason": "Sample 1 | L10 100% | L5 100% | USG 15% | MIN 14.0 | AST matchup 0.98x | Prev 3.0 | Pre 3.0 | Home boost | Minutes watch"
          },
          {
            "player_id": "4790263",
            "player_name": "Iliana Rupert",
            "team": "GS",
            "opponent": "SEA",
            "line": "2+ AST",
            "score": 63.97,
            "confidence": 64,
            "tier": "B",
            "reason": "Sample 11 | L10 60% | L5 60% | USG 26% | MIN 25.7 | AST matchup 1.00x | Prev 2.2 | Pre 2.2 | Anti-correlation: same team as Veronica Burton"
          },
          {
            "player_id": "5017726",
            "player_name": "Jade Melbourne",
            "team": "SEA",
            "opponent": "GS",
            "line": "3+ AST",
            "score": 57.05,
            "confidence": 57,
            "tier": "C",
            "reason": "Sample 12 | L10 70% | L5 60% | USG 17% | MIN 19.5 | AST matchup 0.98x | Prev 3.4 | Pre 2.5 | Home boost | Minutes watch | Anti-correlation: same team as Natisha Hiedeman"
          },
          {
            "player_id": "1054",
            "player_name": "Tiffany Hayes",
            "team": "GS",
            "opponent": "SEA",
            "line": "2+ AST",
            "score": 43.54,
            "confidence": 44,
            "tier": "C",
            "reason": "Sample 2 | L10 50% | L5 50% | USG 16% | MIN 15.5 | AST matchup 1.00x | Prev 3.0 | Pre 1.0 | Decline 0.20 | Minutes watch | Anti-correlation: same team as Veronica Burton"
          },
          {
            "player_id": "4698736",
            "player_name": "Flau'jae Johnson",
            "team": "SEA",
            "opponent": "GS",
            "line": "2+ AST",
            "score": 29.81,
            "confidence": 30,
            "tier": "C",
            "reason": "Sample 2 | L10 0% | L5 0% | USG 35% | MIN 21.0 | AST matchup 0.98x | Prev 0.5 | Pre 0.5 | Home boost | Minutes watch | Anti-correlation: same team as Natisha Hiedeman"
          },
          {
            "player_id": "4066527",
            "player_name": "Jaelyn Brown",
            "team": "SEA",
            "opponent": "GS",
            "line": "2+ AST",
            "score": 22.16,
            "confidence": 22,
            "tier": "C",
            "reason": "Sample 2 | L10 0% | L5 0% | USG 18% | MIN 12.0 | AST matchup 0.98x | Prev 0.5 | Pre 0.5 | Home boost | Minutes watch | Anti-correlation: same team as Natisha Hiedeman"
          },
          {
            "player_id": "2529622",
            "player_name": "Kayla Thornton",
            "team": "GS",
            "opponent": "SEA",
            "line": "2+ AST",
            "score": 21.66,
            "confidence": 22,
            "tier": "C",
            "reason": "Sample 1 | L10 0% | L5 0% | USG 23% | MIN 15.0 | AST matchup 1.00x | Prev 0.0 | Pre 0.0 | Minutes watch | Anti-correlation: same team as Veronica Burton"
          },
          {
            "player_id": "4280888",
            "player_name": "Rennia Davis",
            "team": "SEA",
            "opponent": "GS",
            "line": "2+ AST",
            "score": 16.44,
            "confidence": 16,
            "tier": "C",
            "reason": "Sample 2 | L10 0% | L5 0% | USG 12% | MIN 8.5 | AST matchup 0.98x | Prev 0.5 | Pre 0.5 | Home boost | Minutes watch | Anti-correlation: same team as Natisha Hiedeman"
          },
          {
            "player_id": "5105731",
            "player_name": "Grace VanSlooten",
            "team": "SEA",
            "opponent": "GS",
            "line": "2+ AST",
            "score": 12.16,
            "confidence": 12,
            "tier": "C",
            "reason": "Sample 2 | L10 0% | L5 0% | USG 7% | MIN 15.0 | AST matchup 0.98x | Prev 0.5 | Pre 0.5 | Home boost | Minutes watch | Anti-correlation: same team as Natisha Hiedeman"
          }
        ],
        "3PM": [
          {
            "player_id": "4066527",
            "player_name": "Jaelyn Brown",
            "team": "SEA",
            "opponent": "GS",
            "line": "1+ 3PM",
            "score": 79.25,
            "confidence": 79,
            "tier": "C",
            "reason": "Sample 2 | L10 100% | L5 100% | USG 18% | MIN 12.0 | 3PM matchup 1.13x | Prev 1.0 | Pre 1.0 | Home boost | Minutes watch"
          },
          {
            "player_id": "4790264",
            "player_name": "Janelle Salaun",
            "team": "GS",
            "opponent": "SEA",
            "line": "2+ 3PM",
            "score": 77.05,
            "confidence": 77,
            "tier": "B",
            "reason": "Sample 11 | L10 80% | L5 80% | USG 38% | MIN 33.0 | 3PM matchup 1.03x | Prev 2.5 | Pre 2.5"
          },
          {
            "player_id": "4790263",
            "player_name": "Iliana Rupert",
            "team": "GS",
            "opponent": "SEA",
            "line": "2+ 3PM",
            "score": 73.17,
            "confidence": 73,
            "tier": "B",
            "reason": "Sample 11 | L10 70% | L5 80% | USG 26% | MIN 25.7 | 3PM matchup 1.03x | Prev 2.3 | Pre 2.3 | Decline 0.21 | Anti-correlation: same team as Janelle Salaun"
          },
          {
            "player_id": "2529622",
            "player_name": "Kayla Thornton",
            "team": "GS",
            "opponent": "SEA",
            "line": "1+ 3PM",
            "score": 72.06,
            "confidence": 72,
            "tier": "C",
            "reason": "Sample 1 | L10 100% | L5 100% | USG 23% | MIN 15.0 | 3PM matchup 1.03x | Prev 1.0 | Pre 1.0 | Minutes watch | Anti-correlation: same team as Janelle Salaun"
          },
          {
            "player_id": "1054",
            "player_name": "Tiffany Hayes",
            "team": "GS",
            "opponent": "SEA",
            "line": "1+ 3PM",
            "score": 67.84,
            "confidence": 68,
            "tier": "C",
            "reason": "Sample 2 | L10 100% | L5 100% | USG 16% | MIN 15.5 | 3PM matchup 1.03x | Prev 1.0 | Pre 1.0 | Minutes watch | Anti-correlation: same team as Janelle Salaun"
          },
          {
            "player_id": "4698736",
            "player_name": "Flau'jae Johnson",
            "team": "SEA",
            "opponent": "GS",
            "line": "2+ 3PM",
            "score": 61.15,
            "confidence": 61,
            "tier": "C",
            "reason": "Sample 2 | L10 50% | L5 50% | USG 35% | MIN 21.0 | 3PM matchup 1.13x | Prev 2.0 | Pre 2.0 | Home boost | Minutes watch | Anti-correlation: same team as Jaelyn Brown"
          },
          {
            "player_id": "3906753",
            "player_name": "Natisha Hiedeman",
            "team": "SEA",
            "opponent": "GS",
            "line": "1+ 3PM",
            "score": 24.97,
            "confidence": 25,
            "tier": "C",
            "reason": "Sample 1 | L10 0% | L5 0% | USG 15% | MIN 14.0 | 3PM matchup 1.13x | Prev 0.0 | Pre 0.0 | Home boost | Minutes watch | Anti-correlation: same team as Jaelyn Brown"
          },
          {
            "player_id": "4280888",
            "player_name": "Rennia Davis",
            "team": "SEA",
            "opponent": "GS",
            "line": "1+ 3PM",
            "score": 23.28,
            "confidence": 23,
            "tier": "C",
            "reason": "Sample 2 | L10 0% | L5 0% | USG 12% | MIN 8.5 | 3PM matchup 1.13x | Prev 0.0 | Pre 0.0 | Home boost | Minutes watch | Anti-correlation: same team as Jaelyn Brown"
          },
          {
            "player_id": "5105731",
            "player_name": "Grace VanSlooten",
            "team": "SEA",
            "opponent": "GS",
            "line": "1+ 3PM",
            "score": 19.0,
            "confidence": 19,
            "tier": "C",
            "reason": "Sample 2 | L10 0% | L5 0% | USG 7% | MIN 15.0 | 3PM matchup 1.13x | Prev 0.0 | Pre 0.0 | Home boost | Minutes watch | Anti-correlation: same team as Jaelyn Brown"
          },
          {
            "player_id": "2590093",
            "player_name": "Kiah Stokes",
            "team": "GS",
            "opponent": "SEA",
            "line": "1+ 3PM",
            "score": 11.01,
            "confidence": 11,
            "tier": "C",
            "reason": "Sample 1 | L10 0% | L5 0% | USG 9% | MIN 10.0 | 3PM matchup 1.03x | Prev 0.0 | Pre 0.0 | Minutes watch | Anti-correlation: same team as Janelle Salaun"
          }
        ],
        "ML": [
          {
            "player_id": "sea-moneyline",
            "player_name": "SEA",
            "team": "SEA",
            "opponent": "GS",
            "line": "Moneyline",
            "score": 52.42,
            "confidence": 52,
            "tier": "C",
            "reason": "Recent win 50% | Allow 82.6 PPG"
          }
        ]
      }
    }
  ]
}